{"data":[{"RANK":"1","ATHLETES":"Phan, Kimberly","AGE":"10","YOB":"1996","CLUB":"VAC","PROVINCE":"Ontario","DATE":"2007-10-13","MEET":"Hall of Fame Meet","TIME":"29.98","FINA":"525"},{"RANK":"2","ATHLETES":"Scott, Emily","AGE":"10","YOB":"1997","CLUB":"MUSAC","PROVINCE":"Ontario","DATE":"2008-04-05","MEET":"MuskokaAquatic 3rd Annual Spring Sprint invitational","TIME":"30.15","FINA":"516"},{"RANK":"3","ATHLETES":"Hubert, Melinda","AGE":"10","YOB":"1997","CLUB":"MUSAC","PROVINCE":"Ontario","DATE":"2008-04-05","MEET":"MuskokaAquatic 3rd Annual Spring Sprint invitational","TIME":"30.57","FINA":"495"},{"RANK":"4","ATHLETES":"Sbaraglia, Olivia","AGE":"10","YOB":"1997","CLUB":"DS","PROVINCE":"Ontario","DATE":"2008-02-29","MEET":"Junior Provincial Championships SC","TIME":"30.92","FINA":"479"},{"RANK":"5","ATHLETES":"Meklensek, Lexi","AGE":"10","YOB":"1997","CLUB":"ROW","PROVINCE":"Ontario","DATE":"2008-04-18","MEET":"Division 1 Championships","TIME":"31.18","FINA":"467"},{"RANK":"6","ATHLETES":"Kan, Alicia","AGE":"10","YOB":"1996","CLUB":"SFA","PROVINCE":"British Columbia","DATE":"2007-12-09","MEET":"PCS Xmas Cracker","TIME":"31.21","FINA":"466"},{"RANK":"7","ATHLETES":"Evans, Cody","AGE":"10","YOB":"1997","CLUB":"MM","PROVINCE":"Manitoba","DATE":"2008-01-31","MEET":"Manitoba-Saskatchewan Short Course Championship","TIME":"31.25","FINA":"464"},{"RANK":"8","ATHLETES":"Vuong, Megan","AGE":"10","YOB":"1997","CLUB":"MSSAC","PROVINCE":"Ontario","DATE":"2008-01-19","MEET":"12 & Under Celebration","TIME":"31.41","FINA":"457"},{"RANK":"9","ATHLETES":"Li, May","AGE":"10","YOB":"1997","CLUB":"SFA","PROVINCE":"British Columbia","DATE":"2007-11-11","MEET":"Spartan Invitational Swim Meet","TIME":"31.43","FINA":"456"},{"RANK":"10","ATHLETES":"Blouin, Natalie","AGE":"10","YOB":"1997","CLUB":"MM","PROVINCE":"Manitoba","DATE":"2008-01-31","MEET":"Manitoba-Saskatchewan Short Course Championship","TIME":"31.54","FINA":"451"},{"RANK":"11","ATHLETES":"Thompson, Kasey","AGE":"10","YOB":"1997","CLUB":"SLSC","PROVINCE":"Ontario","DATE":"2008-02-29","MEET":"Junior Provincial Championships SC","TIME":"31.92","FINA":"435"},{"RANK":"12","ATHLETES":"Margitai, Lili","AGE":"10","YOB":"1997","CLUB":"EKSC","PROVINCE":"Alberta","DATE":"2008-03-16","MEET":"2008 Alberta Age Group Provincials SC","TIME":"31.94","FINA":"434"},{"RANK":"13","ATHLETES":"Aktary, Ariana","AGE":"10","YOB":"1997","CLUB":"PSW","PROVINCE":"British Columbia","DATE":"2008-03-01","MEET":"TAS BC Provincial AAA Championships","TIME":"31.95","FINA":"434"},{"RANK":"14","ATHLETES":"Yu, Jessica","AGE":"10","YOB":"1998","CLUB":"NKB","PROVINCE":"Ontario","DATE":"2008-04-18","MEET":"Division 1 Championships","TIME":"31.99","FINA":"432"},{"RANK":"15","ATHLETES":"Bezanson, Taya","AGE":"10","YOB":"1997","CLUB":"COMOX","PROVINCE":"British Columbia","DATE":"2007-12-09","MEET":"PCS Xmas Cracker","TIME":"32.12","FINA":"427"},{"RANK":"16","ATHLETES":"Tan, Clarissa","AGE":"10","YOB":"1997","CLUB":"VPSC","PROVINCE":"British Columbia","DATE":"2008-06-20","MEET":"TAS BC AA Championships","TIME":"32.23","FINA":"423"},{"RANK":"17","ATHLETES":"Kremer, Paige","AGE":"10","YOB":"1996","CLUB":"OSC","PROVINCE":"Alberta","DATE":"2007-10-05","MEET":"OSC Home Opener","TIME":"32.24","FINA":"422"},{"RANK":"18","ATHLETES":"Nguyen, Angeline","AGE":"10","YOB":"1997","CLUB":"DDO","PROVINCE":"Québec","DATE":"2008-05-24","MEET":"Invitation Développement ¨TYR¨ toi à l'eau","TIME":"32.25","FINA":"422"},{"RANK":"19","ATHLETES":"Chow, Maddison","AGE":"10","YOB":"1997","CLUB":"PSW","PROVINCE":"British Columbia","DATE":"2008-02-29","MEET":"TAS BC Provincial AAA Championships","TIME":"32.28","FINA":"421"},{"RANK":"20","ATHLETES":"Fazekas, Sadie","AGE":"10","YOB":"1997","CLUB":"WEST","PROVINCE":"Ontario","DATE":"2008-04-18","MEET":"Division 1 Championships","TIME":"32.29","FINA":"420"},{"RANK":"21","ATHLETES":"Aguiar, Elizabeth","AGE":"10","YOB":"1997","CLUB":"LLSC","PROVINCE":"British Columbia","DATE":"2008-03-01","MEET":"TAS BC Provincial AAA Championships","TIME":"32.31","FINA":"420"},{"RANK":"21","ATHLETES":"Kidd, Georgia","AGE":"10","YOB":"1998","CLUB":"OSC","PROVINCE":"Alberta","DATE":"2008-03-15","MEET":"2008 Alberta Age Group Provincials SC","TIME":"32.31","FINA":"420"},{"RANK":"23","ATHLETES":"Cigna, Frédérique","AGE":"10","YOB":"1997","CLUB":"CAMO","PROVINCE":"Québec","DATE":"2008-04-12","MEET":"Inv. Prov. Dév. Printemps SAMAK","TIME":"32.32","FINA":"419"},{"RANK":"24","ATHLETES":"Brayne, Kimberly","AGE":"10","YOB":"1997","CLUB":"PCSC","PROVINCE":"Québec","DATE":"2008-05-04","MEET":"Semi-Finales régionales ANLSL","TIME":"32.36","FINA":"418"},{"RANK":"25","ATHLETES":"Dalbec, Bayley","AGE":"10","YOB":"1997","CLUB":"COBRA","PROVINCE":"Ontario","DATE":"2008-05-18","MEET":"2008 TOP Cup SC","TIME":"32.52","FINA":"412"},{"RANK":"26","ATHLETES":"Zaraska, Melanya","AGE":"10","YOB":"1997","CLUB":"ESWIM","PROVINCE":"Ontario","DATE":"2008-04-18","MEET":"Division 1 Championships","TIME":"32.59","FINA":"409"},{"RANK":"27","ATHLETES":"Xu, Jier Jill","AGE":"10","YOB":"1997","CLUB":"PSW","PROVINCE":"British Columbia","DATE":"2008-03-01","MEET":"TAS BC Provincial AAA Championships","TIME":"32.63","FINA":"407"},{"RANK":"28","ATHLETES":"Charron, Samie","AGE":"10","YOB":"1997","CLUB":"CNCB","PROVINCE":"Québec","DATE":"2008-02-09","MEET":"Inv. Prov. Dév. Aquafête du Carnaval","TIME":"32.69","FINA":"405"},{"RANK":"28","ATHLETES":"Abdel-khalik, Esraa","AGE":"10","YOB":"1997","CLUB":"ESWIM","PROVINCE":"Ontario","DATE":"2008-01-18","MEET":"AB Meet","TIME":"32.69","FINA":"405"},{"RANK":"28","ATHLETES":"Lo, Angela","AGE":"10","YOB":"1997","CLUB":"UBCSC","PROVINCE":"British Columbia","DATE":"2008-03-01","MEET":"TAS BC Provincial AAA Championships","TIME":"32.69","FINA":"405"},{"RANK":"31","ATHLETES":"Takahashi, Nina","AGE":"10","YOB":"1997","CLUB":"SFA","PROVINCE":"British Columbia","DATE":"2008-03-01","MEET":"TAS BC Provincial AAA Championships","TIME":"32.76","FINA":"403"},{"RANK":"32","ATHLETES":"Singh, Cai Hong","AGE":"10","YOB":"1997","CLUB":"UBCSC","PROVINCE":"British Columbia","DATE":"2008-03-01","MEET":"TAS BC Provincial AAA Championships","TIME":"32.79","FINA":"401"},{"RANK":"33","ATHLETES":"Blackwin, Cassidy","AGE":"10","YOB":"1997","CLUB":"AJAX","PROVINCE":"Ontario","DATE":"2008-02-10","MEET":"2008 Central Region SC Champs","TIME":"32.85","FINA":"399"},{"RANK":"34","ATHLETES":"D'Aoust, Danielle","AGE":"10","YOB":"1997","CLUB":"GMAC","PROVINCE":"Ontario","DATE":"2008-01-12","MEET":"Milton Dash for Cash","TIME":"32.93","FINA":"396"},{"RANK":"35","ATHLETES":"Gervais, Michelle","AGE":"10","YOB":"1997","CLUB":"OAK","PROVINCE":"Ontario","DATE":"2007-11-02","MEET":"Harvest Invitational","TIME":"32.97","FINA":"395"},{"RANK":"36","ATHLETES":"Douglas, Danielle","AGE":"10","YOB":"1996","CLUB":"LLSC","PROVINCE":"British Columbia","DATE":"2007-11-03","MEET":"Halloween Hustle 2007","TIME":"32.99","FINA":"394"},{"RANK":"37","ATHLETES":"Itterman, Tia","AGE":"10","YOB":"1997","CLUB":"KWIC","PROVINCE":"British Columbia","DATE":"2008-06-20","MEET":"TAS BC AA Championships","TIME":"33.04","FINA":"392"},{"RANK":"38","ATHLETES":"Gionet, Christiane","AGE":"10","YOB":"1997","CLUB":"ESWIM","PROVINCE":"Ontario","DATE":"2007-12-09","MEET":"Youth Cup","TIME":"33.10","FINA":"390"},{"RANK":"39","ATHLETES":"Gour, Lee Ann","AGE":"10","YOB":"1997","CLUB":"KBM","PROVINCE":"Ontario","DATE":"2008-02-02","MEET":": 2008 EASTERN ONTARIO REGIONAL SHORT COURSE CHAMPIONSHIPS","TIME":"33.13","FINA":"389"},{"RANK":"40","ATHLETES":"Sauve, Carly","AGE":"10","YOB":"1997","CLUB":"BTSC","PROVINCE":"Ontario","DATE":"2008-02-29","MEET":"Junior Provincial Championships SC","TIME":"33.24","FINA":"385"},{"RANK":"41","ATHLETES":"Parsons, Samantha","AGE":"10","YOB":"1997","CLUB":"DDO","PROVINCE":"Québec","DATE":"2007-12-16","MEET":"Intra-club DDO à Vaudreuil","TIME":"33.29","FINA":"384"},{"RANK":"42","ATHLETES":"Powell, Madison","AGE":"10","YOB":"1997","CLUB":"IS","PROVINCE":"British Columbia","DATE":"2008-03-01","MEET":"TAS BC Provincial AAA Championships","TIME":"33.30","FINA":"383"},{"RANK":"43","ATHLETES":"Wookey, Leah","AGE":"10","YOB":"1997","CLUB":"UCSC","PROVINCE":"Alberta","DATE":"2008-03-15","MEET":"2008 Alberta Age Group Provincials SC","TIME":"33.32","FINA":"383"},{"RANK":"44","ATHLETES":"Zhang, Jenny","AGE":"10","YOB":"1997","CLUB":"ROW","PROVINCE":"Ontario","DATE":"2008-02-02","MEET":"Western Region SC Championships","TIME":"33.33","FINA":"382"},{"RANK":"45","ATHLETES":"Knox, Erica","AGE":"10","YOB":"1996","CLUB":"HHBF","PROVINCE":"Ontario","DATE":"2007-12-01","MEET":"Gord Bassett Invitational","TIME":"33.36","FINA":"381"},{"RANK":"46","ATHLETES":"Lam, Heather","AGE":"10","YOB":"1998","CLUB":"VPSC","PROVINCE":"British Columbia","DATE":"2008-05-10","MEET":"SKSC May LMR","TIME":"33.38","FINA":"381"},{"RANK":"47","ATHLETES":"Nguyen, Mélanie","AGE":"10","YOB":"1997","CLUB":"DDO","PROVINCE":"Québec","DATE":"2008-05-04","MEET":"Semi-Finales régionales ANLSL","TIME":"33.40","FINA":"380"},{"RANK":"48","ATHLETES":"Zhao, Janet","AGE":"10","YOB":"1997","CLUB":"NKB","PROVINCE":"Ontario","DATE":"2008-02-03","MEET":": 2008 EASTERN ONTARIO REGIONAL SHORT COURSE CHAMPIONSHIPS","TIME":"33.51","FINA":"376"},{"RANK":"49","ATHLETES":"Lecky, Alexandra","AGE":"10","YOB":"1997","CLUB":"CSL","PROVINCE":"Ontario","DATE":"2008-02-03","MEET":": 2008 EASTERN ONTARIO REGIONAL SHORT COURSE CHAMPIONSHIPS","TIME":"33.58","FINA":"374"},{"RANK":"50","ATHLETES":"Decarlo, Courtney","AGE":"10","YOB":"1997","CLUB":"BTSC","PROVINCE":"Ontario","DATE":"2008-01-18","MEET":"AB Meet","TIME":"33.59","FINA":"373"}],"errors":[],"meta":{"delimiter":"|","linebreak":"\n","aborted":false,"truncated":false,"cursor":4730,"fields":["RANK","ATHLETES","AGE","YOB","CLUB","PROVINCE","DATE","MEET","TIME","FINA"]}}