{"data":[{"RANK":"1","ATHLETES":"Siwicki, Breanne","AGE":"18","YOB":"1995","CLUB":"MANTA","PROVINCE":"Manitoba","DATE":"2013-02-16","MEET":"Speedo Western Canadian Championships","TIME":"2:12.84","FINA":"751"},{"RANK":"2","ATHLETES":"Marois, Sophie","AGE":"18","YOB":"1995","CLUB":"CASE","PROVINCE":"Québec","DATE":"2013-03-02","MEET":"Championnat provincial Junior et Senior Trophées Dubois d'hiver","TIME":"2:14.66","FINA":"721"},{"RANK":"3","ATHLETES":"Hodge, Caitlin","AGE":"18","YOB":"1994","CLUB":"NG","PROVINCE":"Québec","DATE":"2013-02-16","MEET":"Championnats canadiens de l’Est Speedo 2013","TIME":"2:16.07","FINA":"699"},{"RANK":"4","ATHLETES":"McNaughton, Jennifer","AGE":"18","YOB":"1994","CLUB":"WES","PROVINCE":"Ontario","DATE":"2013-02-07","MEET":"2013 OUA Championships","TIME":"2:16.17","FINA":"697"},{"RANK":"5","ATHLETES":"Sayer, Abigail","AGE":"18","YOB":"1994","CLUB":"UOFC","PROVINCE":"Alberta","DATE":"2013-01-27","MEET":"Canada West University Championships","TIME":"2:16.50","FINA":"692"},{"RANK":"6","ATHLETES":"Newman, Rachael","AGE":"18","YOB":"1994","CLUB":"UVIC","PROVINCE":"British Columbia","DATE":"2013-01-27","MEET":"Canada West University Championships","TIME":"2:16.70","FINA":"689"},{"RANK":"7","ATHLETES":"Moy, Nathalin","AGE":"18","YOB":"1994","CLUB":"UT","PROVINCE":"Ontario","DATE":"2012-12-01","MEET":"University of Toronto/ Western University Dual Swim Meet","TIME":"2:17.38","FINA":"679"},{"RANK":"8","ATHLETES":"Richard, Claudie","AGE":"18","YOB":"1994","CLUB":"CSQ","PROVINCE":"Québec","DATE":"2012-12-07","MEET":"2012 Paul Bergen Jr. International","TIME":"2:18.69","FINA":"660"},{"RANK":"9","ATHLETES":"Carnevale, Paolina","AGE":"18","YOB":"1994","CLUB":"ESWIM","PROVINCE":"Ontario","DATE":"2013-07-10","MEET":"July 10 Time Trial","TIME":"2:18.89","FINA":"657"},{"RANK":"10","ATHLETES":"Pierse, Patricia","AGE":"18","YOB":"1994","CLUB":"UBCT","PROVINCE":"British Columbia","DATE":"2013-01-27","MEET":"Canada West University Championships","TIME":"2:18.95","FINA":"656"},{"RANK":"11","ATHLETES":"Skocdopole, Alana","AGE":"18","YOB":"1994","CLUB":"UOFC","PROVINCE":"Alberta","DATE":"2013-01-27","MEET":"Canada West University Championships","TIME":"2:19.84","FINA":"644"},{"RANK":"12","ATHLETES":"Oswald, Hannah","AGE":"18","YOB":"1995","CLUB":"WEST","PROVINCE":"Ontario","DATE":"2013-02-16","MEET":"Championnats canadiens de l’Est Speedo 2013","TIME":"2:20.31","FINA":"637"},{"RANK":"13","ATHLETES":"Murphy, Gabrielle","AGE":"18","YOB":"1995","CLUB":"PCSC","PROVINCE":"Québec","DATE":"2013-03-02","MEET":"Championnat provincial Junior et Senior Trophées Dubois d'hiver","TIME":"2:20.38","FINA":"636"},{"RANK":"14","ATHLETES":"Jewell, Karyn","AGE":"18","YOB":"1993","CLUB":"NG","PROVINCE":"Québec","DATE":"2012-11-04","MEET":"Coupe du Québec 1, Junior et Senior","TIME":"2:20.45","FINA":"635"},{"RANK":"15","ATHLETES":"Wey, Tess","AGE":"18","YOB":"1994","CLUB":"UG","PROVINCE":"Ontario","DATE":"2013-02-07","MEET":"2013 OUA Championships","TIME":"2:20.57","FINA":"634"},{"RANK":"16","ATHLETES":"Noël, Camille","AGE":"18","YOB":"1994","CLUB":"CAMO","PROVINCE":"Québec","DATE":"2013-02-16","MEET":"Championnats canadiens de l’Est Speedo 2013","TIME":"2:20.79","FINA":"631"},{"RANK":"17","ATHLETES":"Papadedes, Stephanie","AGE":"18","YOB":"1994","CLUB":"UG","PROVINCE":"Ontario","DATE":"2013-02-07","MEET":"2013 OUA Championships","TIME":"2:22.18","FINA":"613"},{"RANK":"18","ATHLETES":"Mastromatteo, Monica","AGE":"18","YOB":"1994","CLUB":"MCGILL","PROVINCE":"Québec","DATE":"2012-11-17","MEET":"AUS Invitational","TIME":"2:23.41","FINA":"597"},{"RANK":"19","ATHLETES":"Lapointe, Marie-Lou","AGE":"18","YOB":"1994","CLUB":"CAMO","PROVINCE":"Québec","DATE":"2012-12-16","MEET":"Inv P1-P2 Noël 2012, CAMO natation","TIME":"2:23.45","FINA":"596"},{"RANK":"20","ATHLETES":"Declark, Kara","AGE":"18","YOB":"1994","CLUB":"UOFL","PROVINCE":"Alberta","DATE":"2012-11-30","MEET":"JP Fiset International","TIME":"2:23.61","FINA":"594"},{"RANK":"21","ATHLETES":"Webster, Katherine","AGE":"18","YOB":"1993","CLUB":"DAL","PROVINCE":"Nova Scotia","DATE":"2012-11-03","MEET":"4th Annual Jack Scholz AUS Invitational Meet","TIME":"2:24.31","FINA":"586"},{"RANK":"22","ATHLETES":"Cieplucha, Sophie","AGE":"18","YOB":"1994","CLUB":"COBRA","PROVINCE":"Ontario","DATE":"2013-02-16","MEET":"Championnats canadiens de l’Est Speedo 2013","TIME":"2:24.62","FINA":"582"},{"RANK":"23","ATHLETES":"Mann, Julia","AGE":"18","YOB":"1995","CLUB":"MM","PROVINCE":"Manitoba","DATE":"2013-02-16","MEET":"Speedo Western Canadian Championships","TIME":"2:24.64","FINA":"582"},{"RANK":"24","ATHLETES":"Andrew, Amy","AGE":"18","YOB":"1994","CLUB":"RDCSC","PROVINCE":"Alberta","DATE":"2013-02-01","MEET":"2013 Speedo Senior Champs Short Course","TIME":"2:25.22","FINA":"575"},{"RANK":"25","ATHLETES":"Starman, Sabra","AGE":"18","YOB":"1994","CLUB":"UOFL","PROVINCE":"Alberta","DATE":"2013-01-27","MEET":"Canada West University Championships","TIME":"2:26.01","FINA":"566"},{"RANK":"26","ATHLETES":"Langlois-Pelletier, Mileva","AGE":"18","YOB":"1994","CLUB":"SAMAK","PROVINCE":"Québec","DATE":"2013-02-16","MEET":"Championnats canadiens de l’Est Speedo 2013","TIME":"2:26.56","FINA":"559"},{"RANK":"27","ATHLETES":"Serka, Stefanie","AGE":"18","YOB":"1994","CLUB":"UBCSC","PROVINCE":"British Columbia","DATE":"2013-02-16","MEET":"Speedo Western Canadian Championships","TIME":"2:26.69","FINA":"558"},{"RANK":"28","ATHLETES":"Théberge, Marie-Michele","AGE":"18","YOB":"1995","CLUB":"GAMIN","PROVINCE":"Québec","DATE":"2013-05-04","MEET":"Festival par équipe - Section 5 Nord","TIME":"2:27.61","FINA":"547"},{"RANK":"29","ATHLETES":"Rogers, Alison","AGE":"18","YOB":"1994","CLUB":"UG","PROVINCE":"Ontario","DATE":"2013-02-07","MEET":"2013 OUA Championships","TIME":"2:29.48","FINA":"527"},{"RANK":"30","ATHLETES":"Smelt, Miranda","AGE":"18","YOB":"1994","CLUB":"WLU","PROVINCE":"Ontario","DATE":"2013-02-07","MEET":"2013 OUA Championships","TIME":"2:29.58","FINA":"526"},{"RANK":"31","ATHLETES":"Jardine, Caitlin","AGE":"18","YOB":"1994","CLUB":"QUE","PROVINCE":"Ontario","DATE":"2013-02-07","MEET":"2013 OUA Championships","TIME":"2:29.94","FINA":"522"},{"RANK":"32","ATHLETES":"Macmillan, Laura","AGE":"18","YOB":"1994","CLUB":"HTAC","PROVINCE":"Nova Scotia","DATE":"2013-03-03","MEET":"2013 East Coast Short Course Championships","TIME":"2:30.11","FINA":"520"},{"RANK":"33","ATHLETES":"Labaj, Alexandra","AGE":"18","YOB":"1994","CLUB":"GMAC","PROVINCE":"Ontario","DATE":"2012-12-07","MEET":"Team Aquatic Supplies Dash for Cash","TIME":"2:30.71","FINA":"514"},{"RANK":"34","ATHLETES":"Macpherson, Kristen","AGE":"18","YOB":"1993","CLUB":"ACAD","PROVINCE":"Nova Scotia","DATE":"2012-11-17","MEET":"AUS Invitational","TIME":"2:31.13","FINA":"510"},{"RANK":"34","ATHLETES":"Paquin-Foisy, Elisabeth","AGE":"18","YOB":"1994","CLUB":"ELITE","PROVINCE":"Québec","DATE":"2013-04-26","MEET":"Festival par équipe - Section 2","TIME":"2:31.13","FINA":"510"},{"RANK":"36","ATHLETES":"Sehn, Rachel","AGE":"18","YOB":"1994","CLUB":"BADGR","PROVINCE":"Ontario","DATE":"2013-01-19","MEET":"Ontario Cup","TIME":"2:31.16","FINA":"510"},{"RANK":"37","ATHLETES":"Bellio, Olivia","AGE":"18","YOB":"1994","CLUB":"ESWIM","PROVINCE":"Ontario","DATE":"2013-01-19","MEET":"2013 A-B Meet","TIME":"2:31.20","FINA":"509"},{"RANK":"38","ATHLETES":"Boisvenue, Frédérique","AGE":"18","YOB":"1993","CLUB":"LAVAL","PROVINCE":"Québec","DATE":"2012-12-14","MEET":"Invitation Pointe-Claire Provincial 2 2012","TIME":"2:31.32","FINA":"508"},{"RANK":"39","ATHLETES":"Dion, Marie-Hélène","AGE":"18","YOB":"1994","CLUB":"CAO","PROVINCE":"Québec","DATE":"2013-01-29","MEET":"Intramurale CAO janvier 2013","TIME":"2:31.47","FINA":"506"},{"RANK":"40","ATHLETES":"Bush, Melody","AGE":"18","YOB":"1994","CLUB":"GMAC","PROVINCE":"Ontario","DATE":"2013-02-03","MEET":"Western Region SC Championships","TIME":"2:32.18","FINA":"499"},{"RANK":"41","ATHLETES":"Adam, Lauren","AGE":"18","YOB":"1995","CLUB":"FAST","PROVINCE":"New Brunswick","DATE":"2013-03-03","MEET":"2013 East Coast Short Course Championships","TIME":"2:32.20","FINA":"499"},{"RANK":"42","ATHLETES":"Osmond, Reeghan","AGE":"18","YOB":"1994","CLUB":"UVIC","PROVINCE":"British Columbia","DATE":"2013-01-27","MEET":"Canada West University Championships","TIME":"2:32.41","FINA":"497"},{"RANK":"43","ATHLETES":"Shrimpton, Claire","AGE":"18","YOB":"1994","CLUB":"PGB","PROVINCE":"British Columbia","DATE":"2012-11-16","MEET":"2012 Medical Northern Sprint Swim Meet","TIME":"2:32.63","FINA":"495"},{"RANK":"44","ATHLETES":"Godawa, Lily","AGE":"18","YOB":"1994","CLUB":"WLU","PROVINCE":"Ontario","DATE":"2012-11-18","MEET":"OUA Tihanyi / Stratten Division Championships","TIME":"2:32.80","FINA":"493"},{"RANK":"45","ATHLETES":"Nolet, Isabelle","AGE":"18","YOB":"1994","CLUB":"CASE","PROVINCE":"Québec","DATE":"2012-12-16","MEET":"Invitation de Noël","TIME":"2:32.95","FINA":"492"},{"RANK":"46","ATHLETES":"Russell, Alison","AGE":"18","YOB":"1994","CLUB":"MACU","PROVINCE":"Ontario","DATE":"2012-11-18","MEET":"OUA Tihanyi / Stratten Division Championships","TIME":"2:33.20","FINA":"490"},{"RANK":"47","ATHLETES":"Chambers, Jessica","AGE":"18","YOB":"1994","CLUB":"SYD","PROVINCE":"Ontario","DATE":"2012-12-15","MEET":"Division 3 Team Champs","TIME":"2:33.50","FINA":"487"},{"RANK":"48","ATHLETES":"Landry, Marilou","AGE":"18","YOB":"1994","CLUB":"CNSH","PROVINCE":"Québec","DATE":"2013-01-19","MEET":"Coupe du Québec 2 - Junior et Senior","TIME":"2:35.58","FINA":"467"},{"RANK":"49","ATHLETES":"Vydelingum, Meaghen","AGE":"18","YOB":"1994","CLUB":"WAT","PROVINCE":"Ontario","DATE":"2013-02-07","MEET":"2013 OUA Championships","TIME":"2:36.21","FINA":"462"},{"RANK":"50","ATHLETES":"Sotiropoulos, Tina","AGE":"18","YOB":"1994","CLUB":"TSC","PROVINCE":"Ontario","DATE":"2013-03-02","MEET":"Newmarket Stingrays Invitational Meet","TIME":"2:36.27","FINA":"461"}],"errors":[],"meta":{"delimiter":"|","linebreak":"\n","aborted":false,"truncated":false,"cursor":5017,"fields":["RANK","ATHLETES","AGE","YOB","CLUB","PROVINCE","DATE","MEET","TIME","FINA"]}}