{"data":[{"RANK":"1","ATHLETES":"Cantin, Geneviève","AGE":"18","YOB":"1991","CLUB":"UL","PROVINCE":"Québec","DATE":"2009-11-27","MEET":"2009 Canada Cup","TIME":"2:08.16","FINA":"881"},{"RANK":"2","ATHLETES":"Schultz, Paige","AGE":"18","YOB":"1991","CLUB":"TSC","PROVINCE":"Ontario","DATE":"2009-11-27","MEET":"2009 Canada Cup","TIME":"2:09.65","FINA":"851"},{"RANK":"3","ATHLETES":"Jardin, Barbara","AGE":"18","YOB":"1991","CLUB":"PPO","PROVINCE":"Québec","DATE":"2009-11-27","MEET":"2009 Canada Cup","TIME":"2:13.09","FINA":"787"},{"RANK":"4","ATHLETES":"Caldwell, Hilary","AGE":"18","YOB":"1991","CLUB":"PSW","PROVINCE":"British Columbia","DATE":"2009-11-27","MEET":"2009 Canada Cup","TIME":"2:13.35","FINA":"782"},{"RANK":"5","ATHLETES":"Fyfe, Nicole","AGE":"18","YOB":"1992","CLUB":"TYEE","PROVINCE":"British Columbia","DATE":"2010-03-06","MEET":"TAS SwimBC AAA Short Course Championships","TIME":"2:15.48","FINA":"746"},{"RANK":"6","ATHLETES":"Landry, Taryne","AGE":"18","YOB":"1991","CLUB":"UBCT","PROVINCE":"British Columbia","DATE":"2010-02-20","MEET":"CIS Swimming Championships","TIME":"2:15.87","FINA":"740"},{"RANK":"7","ATHLETES":"Miller, Paige","AGE":"18","YOB":"1991","CLUB":"COBRA","PROVINCE":"Ontario","DATE":"2009-12-11","MEET":"Invitation provinciale P1-P2, Noël 2009","TIME":"2:16.20","FINA":"734"},{"RANK":"8","ATHLETES":"Sharpe, Rebecca","AGE":"18","YOB":"1991","CLUB":"UT","PROVINCE":"Ontario","DATE":"2010-02-20","MEET":"CIS Swimming Championships","TIME":"2:16.87","FINA":"724"},{"RANK":"9","ATHLETES":"Ranger, Sarah-Jade","AGE":"18","YOB":"1992","CLUB":"CNNG","PROVINCE":"Québec","DATE":"2010-02-20","MEET":"2010 Speedo Eastern Canadian Championships","TIME":"2:16.91","FINA":"723"},{"RANK":"10","ATHLETES":"Montgomery, Olivia","AGE":"18","YOB":"1991","CLUB":"UBCSC","PROVINCE":"British Columbia","DATE":"2009-12-11","MEET":"Paul Bergen Junior International","TIME":"2:17.14","FINA":"719"},{"RANK":"11","ATHLETES":"Flemington, Bethany","AGE":"18","YOB":"1991","CLUB":"UG","PROVINCE":"Ontario","DATE":"2009-12-12","MEET":"Team Aquatic Supplies Dash for Cash","TIME":"2:17.81","FINA":"709"},{"RANK":"12","ATHLETES":"Lemieux, Roxane","AGE":"18","YOB":"1991","CLUB":"TNTC","PROVINCE":"Québec","DATE":"2010-02-20","MEET":"2010 Speedo Eastern Canadian Championships","TIME":"2:18.54","FINA":"698"},{"RANK":"13","ATHLETES":"Rolin, Chelsea","AGE":"18","YOB":"1991","CLUB":"PCSC","PROVINCE":"Québec","DATE":"2009-11-27","MEET":"2009 Canada Cup","TIME":"2:19.06","FINA":"690"},{"RANK":"14","ATHLETES":"Buna, Brittany","AGE":"18","YOB":"1992","CLUB":"VASC","PROVINCE":"British Columbia","DATE":"2010-03-06","MEET":"TAS SwimBC AAA Short Course Championships","TIME":"2:19.57","FINA":"682"},{"RANK":"15","ATHLETES":"Bancescu, Samantha","AGE":"18","YOB":"1991","CLUB":"UT","PROVINCE":"Ontario","DATE":"2010-02-20","MEET":"CIS Swimming Championships","TIME":"2:19.87","FINA":"678"},{"RANK":"16","ATHLETES":"Fleming, Kimberly","AGE":"18","YOB":"1991","CLUB":"MSSAC","PROVINCE":"Ontario","DATE":"2009-11-27","MEET":"2009 Canada Cup","TIME":"2:19.98","FINA":"676"},{"RANK":"17","ATHLETES":"Mielnichuk, Bobbie","AGE":"18","YOB":"1991","CLUB":"UOFA","PROVINCE":"Alberta","DATE":"2009-12-05","MEET":"OSC JP Fiset Invitational","TIME":"2:20.00","FINA":"676"},{"RANK":"18","ATHLETES":"Trung, Jennifer","AGE":"18","YOB":"1991","CLUB":"UWO","PROVINCE":"Ontario","DATE":"2010-02-05","MEET":"Ontario University Championships","TIME":"2:20.09","FINA":"675"},{"RANK":"19","ATHLETES":"Sproule, Sasha","AGE":"18","YOB":"1990","CLUB":"UOFA","PROVINCE":"Alberta","DATE":"2009-12-05","MEET":"OSC JP Fiset Invitational","TIME":"2:20.10","FINA":"675"},{"RANK":"20","ATHLETES":"Treasure, Vanessa","AGE":"18","YOB":"1992","CLUB":"MSSAC","PROVINCE":"Ontario","DATE":"2010-04-18","MEET":"Division 1 Team Championships","TIME":"2:20.23","FINA":"673"},{"RANK":"21","ATHLETES":"Corriveau, Emmalina","AGE":"18","YOB":"1991","CLUB":"DAL","PROVINCE":"Nova Scotia","DATE":"2010-02-20","MEET":"CIS Swimming Championships","TIME":"2:20.53","FINA":"669"},{"RANK":"22","ATHLETES":"Jones, Emily","AGE":"18","YOB":"1991","CLUB":"LU","PROVINCE":"Ontario","DATE":"2010-02-20","MEET":"CIS Swimming Championships","TIME":"2:21.97","FINA":"648"},{"RANK":"23","ATHLETES":"Gow, Julia","AGE":"18","YOB":"1990","CLUB":"DAL","PROVINCE":"Nova Scotia","DATE":"2009-11-27","MEET":"2009 Canada Cup","TIME":"2:22.25","FINA":"645"},{"RANK":"24","ATHLETES":"Singleton-Fookes, Morgan","AGE":"18","YOB":"1991","CLUB":"UWO","PROVINCE":"Ontario","DATE":"2010-02-20","MEET":"CIS Swimming Championships","TIME":"2:22.35","FINA":"643"},{"RANK":"25","ATHLETES":"Martin, Carly","AGE":"18","YOB":"1991","CLUB":"WLU","PROVINCE":"Ontario","DATE":"2010-02-20","MEET":"CIS Swimming Championships","TIME":"2:22.42","FINA":"642"},{"RANK":"26","ATHLETES":"Heard, Kaleigh","AGE":"18","YOB":"1991","CLUB":"UWO","PROVINCE":"Ontario","DATE":"2009-11-14","MEET":"OUA Bob Eynon Sr. Divisional Championships 2009","TIME":"2:22.49","FINA":"641"},{"RANK":"27","ATHLETES":"Smith, Kelsey","AGE":"18","YOB":"1991","CLUB":"UOFA","PROVINCE":"Alberta","DATE":"2010-01-23","MEET":"Canada West Swimming Championships","TIME":"2:22.95","FINA":"635"},{"RANK":"28","ATHLETES":"Bayliss, Chantel","AGE":"18","YOB":"1992","CLUB":"KAJ","PROVINCE":"British Columbia","DATE":"2010-03-06","MEET":"TAS SwimBC AAA Short Course Championships","TIME":"2:23.02","FINA":"634"},{"RANK":"29","ATHLETES":"Marcotte, Sophie","AGE":"18","YOB":"1991","CLUB":"CSQ","PROVINCE":"Québec","DATE":"2009-12-11","MEET":"Invitation provinciale P1-P2, Noël 2009","TIME":"2:23.96","FINA":"622"},{"RANK":"30","ATHLETES":"Paradis, Jasmine","AGE":"18","YOB":"1991","CLUB":"MEGO","PROVINCE":"Québec","DATE":"2010-02-26","MEET":"Championnat provincial Aquam groupes d'âge et senior","TIME":"2:24.01","FINA":"621"},{"RANK":"31","ATHLETES":"Wood, Allison","AGE":"18","YOB":"1991","CLUB":"UVIC","PROVINCE":"British Columbia","DATE":"2010-02-20","MEET":"CIS Swimming Championships","TIME":"2:24.58","FINA":"614"},{"RANK":"32","ATHLETES":"Toro, Michelle","AGE":"18","YOB":"1991","CLUB":"NYAC","PROVINCE":"Ontario","DATE":"2009-11-14","MEET":"Swim International 2009","TIME":"2:24.82","FINA":"611"},{"RANK":"33","ATHLETES":"Cowan, Keri-Ann","AGE":"18","YOB":"1992","CLUB":"CP","PROVINCE":"Alberta","DATE":"2010-02-20","MEET":"2010 Speedo Western Canadian Championships","TIME":"2:25.19","FINA":"606"},{"RANK":"34","ATHLETES":"Nowlan, Shaneese","AGE":"18","YOB":"1991","CLUB":"UBCT","PROVINCE":"British Columbia","DATE":"2009-11-07","MEET":"Cascade 2009 Slingshot Speed Meet (Gold)","TIME":"2:25.59","FINA":"601"},{"RANK":"35","ATHLETES":"Mendonca, Laura","AGE":"18","YOB":"1991","CLUB":"BBF","PROVINCE":"Québec","DATE":"2010-02-20","MEET":"2010 Speedo Eastern Canadian Championships","TIME":"2:25.78","FINA":"599"},{"RANK":"36","ATHLETES":"Schabler, Tahsha","AGE":"18","YOB":"1990","CLUB":"UOFL","PROVINCE":"Alberta","DATE":"2009-10-17","MEET":"MUN vs UofL","TIME":"2:26.02","FINA":"596"},{"RANK":"37","ATHLETES":"Lebeau, Justine","AGE":"18","YOB":"1991","CLUB":"TNTC","PROVINCE":"Québec","DATE":"2010-02-26","MEET":"Championnat provincial Aquam groupes d'âge et senior","TIME":"2:26.31","FINA":"592"},{"RANK":"38","ATHLETES":"Kilty, Paulyne","AGE":"18","YOB":"1991","CLUB":"UWO","PROVINCE":"Ontario","DATE":"2010-01-17","MEET":"Ontario Cup","TIME":"2:26.40","FINA":"591"},{"RANK":"39","ATHLETES":"Tsang, Vivian","AGE":"18","YOB":"1992","CLUB":"VPSC","PROVINCE":"British Columbia","DATE":"2010-03-06","MEET":"TAS SwimBC AAA Short Course Championships","TIME":"2:26.87","FINA":"586"},{"RANK":"40","ATHLETES":"Forsyth, Riordan","AGE":"18","YOB":"1990","CLUB":"UCSC","PROVINCE":"Alberta","DATE":"2009-12-12","MEET":"Kamloops Ice Classic","TIME":"2:27.15","FINA":"582"},{"RANK":"41","ATHLETES":"Harricharan, Alisha","AGE":"18","YOB":"1991","CLUB":"COBRA","PROVINCE":"Ontario","DATE":"2009-12-11","MEET":"Invitation provinciale P1-P2, Noël 2009","TIME":"2:27.28","FINA":"581"},{"RANK":"42","ATHLETES":"Newell, Siobhan","AGE":"18","YOB":"1991","CLUB":"UVIC","PROVINCE":"British Columbia","DATE":"2009-12-12","MEET":"2009 PCS Xmas Cracker SC Invitational","TIME":"2:27.98","FINA":"573"},{"RANK":"43","ATHLETES":"Smith, Beth","AGE":"18","YOB":"1992","CLUB":"HTAC","PROVINCE":"Nova Scotia","DATE":"2010-06-04","MEET":"2010 Ken Dunn Championships","TIME":"2:28.37","FINA":"568"},{"RANK":"44","ATHLETES":"Macpherson, Ceilidh","AGE":"18","YOB":"1992","CLUB":"WTSC","PROVINCE":"Nova Scotia","DATE":"2010-07-03","MEET":"Acadia Senior Summer Splash","TIME":"2:28.40","FINA":"568"},{"RANK":"45","ATHLETES":"Evans, Elana","AGE":"18","YOB":"1992","CLUB":"MCGILL","PROVINCE":"Québec","DATE":"2010-02-20","MEET":"CIS Swimming Championships","TIME":"2:28.70","FINA":"564"},{"RANK":"46","ATHLETES":"Plante, Anne-Sophie","AGE":"18","YOB":"1991","CLUB":"CSQ","PROVINCE":"Québec","DATE":"2010-02-20","MEET":"2010 Speedo Eastern Canadian Championships","TIME":"2:29.08","FINA":"560"},{"RANK":"47","ATHLETES":"Harrigan, Callie","AGE":"18","YOB":"1991","CLUB":"WEST","PROVINCE":"Ontario","DATE":"2010-02-06","MEET":"Western Ontario Regional SC Championship","TIME":"2:29.17","FINA":"559"},{"RANK":"48","ATHLETES":"Suominen, Saara","AGE":"18","YOB":"1992","CLUB":"CAO","PROVINCE":"Québec","DATE":"2010-02-20","MEET":"2010 Speedo Eastern Canadian Championships","TIME":"2:29.20","FINA":"559"},{"RANK":"48","ATHLETES":"Grove, Molly","AGE":"18","YOB":"1991","CLUB":"UBCT","PROVINCE":"British Columbia","DATE":"2009-10-31","MEET":"Swim BC Senior Circuit Meet #1","TIME":"2:29.20","FINA":"559"},{"RANK":"50","ATHLETES":"Luke, Bret","AGE":"18","YOB":"1992","CLUB":"MANTA","PROVINCE":"Manitoba","DATE":"2010-03-20","MEET":"2010 ManSask Short Course Provincial Championships","TIME":"2:29.38","FINA":"557"}],"errors":[],"meta":{"delimiter":"|","linebreak":"\n","aborted":false,"truncated":false,"cursor":4893,"fields":["RANK","ATHLETES","AGE","YOB","CLUB","PROVINCE","DATE","MEET","TIME","FINA"]}}