{"data":[{"RANK":"1","ATHLETES":"Desjarlais, Liam","AGE":"15","YOB":"1996","CLUB":"NN","PROVINCE":"Québec","DATE":"2011-12-09","MEET":"13th Annual Paul Bergen Junior Int'l Invitational","TIME":"1:51.33","FINA":"711"},{"RANK":"2","ATHLETES":"Lyons, Anthony","AGE":"15","YOB":"1996","CLUB":"CASC","PROVINCE":"Alberta","DATE":"2012-02-19","MEET":"2012 Speedo Western Canadian Championships","TIME":"1:51.35","FINA":"710"},{"RANK":"3","ATHLETES":"Kalp, Teddy","AGE":"15","YOB":"1996","CLUB":"NYAC","PROVINCE":"Ontario","DATE":"2012-02-16","MEET":"2012 Speedo Eastern Canadian Championships","TIME":"1:51.75","FINA":"703"},{"RANK":"4","ATHLETES":"Straszynski, Oliver","AGE":"15","YOB":"1996","CLUB":"TSC","PROVINCE":"Ontario","DATE":"2012-03-01","MEET":"2012 SC Junior & PARA Provincials","TIME":"1:51.87","FINA":"700"},{"RANK":"5","ATHLETES":"McGillivray, Scott","AGE":"15","YOB":"1995","CLUB":"CASC","PROVINCE":"Alberta","DATE":"2011-11-06","MEET":"Cascade Speed Meet \"GOLD\"","TIME":"1:52.91","FINA":"681"},{"RANK":"6","ATHLETES":"Cote, Tristan","AGE":"15","YOB":"1995","CLUB":"ESWIM","PROVINCE":"Ontario","DATE":"2011-12-04","MEET":"Youth Cup","TIME":"1:53.13","FINA":"677"},{"RANK":"7","ATHLETES":"Ferraro, Mitchel","AGE":"15","YOB":"1996","CLUB":"USC","PROVINCE":"Ontario","DATE":"2012-03-01","MEET":"2012 SC Junior & PARA Provincials","TIME":"1:53.24","FINA":"675"},{"RANK":"8","ATHLETES":"Lee, Gabriel","AGE":"15","YOB":"1996","CLUB":"WDSC","PROVINCE":"British Columbia","DATE":"2012-03-02","MEET":"2012 TAS SwimBC SC AAA Championships","TIME":"1:53.53","FINA":"670"},{"RANK":"9","ATHLETES":"Beatty, Kyle","AGE":"15","YOB":"1996","CLUB":"CASC","PROVINCE":"Alberta","DATE":"2012-02-19","MEET":"2012 Speedo Western Canadian Championships","TIME":"1:53.65","FINA":"668"},{"RANK":"10","ATHLETES":"Desjardins-Labelle, Alexandre","AGE":"15","YOB":"1996","CLUB":"NG","PROVINCE":"Québec","DATE":"2012-02-26","MEET":"Championnat provincial AQUAM groupes d'âge","TIME":"1:53.81","FINA":"665"},{"RANK":"11","ATHLETES":"Brothers, Peter","AGE":"15","YOB":"1996","CLUB":"VASC","PROVINCE":"British Columbia","DATE":"2012-03-02","MEET":"2012 TAS SwimBC SC AAA Championships","TIME":"1:53.89","FINA":"664"},{"RANK":"12","ATHLETES":"Kosiorek, Lukasz","AGE":"15","YOB":"1996","CLUB":"TSC","PROVINCE":"Ontario","DATE":"2011-12-02","MEET":"Youth Cup","TIME":"1:55.23","FINA":"641"},{"RANK":"13","ATHLETES":"Kwiecien-Delaney, Bryce","AGE":"15","YOB":"1996","CLUB":"OAK","PROVINCE":"Ontario","DATE":"2011-12-02","MEET":"Youth Cup","TIME":"1:55.27","FINA":"640"},{"RANK":"14","ATHLETES":"Li, Bill","AGE":"15","YOB":"1995","CLUB":"VPSC","PROVINCE":"British Columbia","DATE":"2011-12-09","MEET":"13th Annual Paul Bergen Junior Int'l Invitational","TIME":"1:55.46","FINA":"637"},{"RANK":"15","ATHLETES":"Ackman, Matthew","AGE":"15","YOB":"1996","CLUB":"PCSC","PROVINCE":"Québec","DATE":"2012-02-26","MEET":"Championnat provincial AQUAM groupes d'âge","TIME":"1:55.52","FINA":"636"},{"RANK":"16","ATHLETES":"De Costa, Brandon","AGE":"15","YOB":"1996","CLUB":"RAPID","PROVINCE":"British Columbia","DATE":"2011-12-02","MEET":"FastSwim Classic","TIME":"1:55.55","FINA":"635"},{"RANK":"17","ATHLETES":"Yungman, Saveli","AGE":"15","YOB":"1996","CLUB":"PGB","PROVINCE":"British Columbia","DATE":"2012-03-02","MEET":"2012 TAS SwimBC SC AAA Championships","TIME":"1:55.87","FINA":"630"},{"RANK":"18","ATHLETES":"Murphy, Jean-François","AGE":"15","YOB":"1996","CLUB":"PCSC","PROVINCE":"Québec","DATE":"2012-08-01","MEET":"Finale provinciale des Jeux du Québec 2012","TIME":"1:56.33","FINA":"623"},{"RANK":"19","ATHLETES":"Jin, Alexander","AGE":"15","YOB":"1997","CLUB":"NYAC","PROVINCE":"Ontario","DATE":"2012-08-18","MEET":"2012 Ontario Summer Games","TIME":"1:56.34","FINA":"623"},{"RANK":"20","ATHLETES":"Bertrand, David","AGE":"15","YOB":"1996","CLUB":"PCSC","PROVINCE":"Québec","DATE":"2011-12-18","MEET":"Invitation Pointe-Claire Provincial 2 2011","TIME":"1:56.80","FINA":"615"},{"RANK":"21","ATHLETES":"Howe, Ryan","AGE":"15","YOB":"1996","CLUB":"UVPCS","PROVINCE":"British Columbia","DATE":"2011-12-09","MEET":"2011 PCS Xmas Cracker Invitational","TIME":"1:56.93","FINA":"613"},{"RANK":"22","ATHLETES":"White, Evan","AGE":"15","YOB":"1996","CLUB":"OAK","PROVINCE":"Ontario","DATE":"2011-12-02","MEET":"Youth Cup","TIME":"1:57.09","FINA":"611"},{"RANK":"23","ATHLETES":"Caron, Marc-Olivier","AGE":"15","YOB":"1996","CLUB":"CAO","PROVINCE":"Québec","DATE":"2012-02-26","MEET":"Championnat provincial AQUAM groupes d'âge","TIME":"1:57.10","FINA":"611"},{"RANK":"24","ATHLETES":"Bayne, Connor","AGE":"15","YOB":"1996","CLUB":"CASC","PROVINCE":"Alberta","DATE":"2012-02-16","MEET":"2012 Speedo Western Canadian Championships","TIME":"1:57.15","FINA":"610"},{"RANK":"25","ATHLETES":"Hernandez, Nicolas","AGE":"15","YOB":"1995","CLUB":"CHENA","PROVINCE":"British Columbia","DATE":"2011-12-11","MEET":"13th Annual Paul Bergen Junior Int'l Invitational","TIME":"1:57.18","FINA":"609"},{"RANK":"26","ATHLETES":"Blondal, Ben","AGE":"15","YOB":"1996","CLUB":"UCSC","PROVINCE":"Alberta","DATE":"2012-02-19","MEET":"2012 Speedo Western Canadian Championships","TIME":"1:57.25","FINA":"608"},{"RANK":"27","ATHLETES":"Chen, Zao","AGE":"15","YOB":"1996","CLUB":"NKB","PROVINCE":"Ontario","DATE":"2012-03-01","MEET":"2012 SC Junior & PARA Provincials","TIME":"1:57.35","FINA":"607"},{"RANK":"28","ATHLETES":"Leung, Ho Yin","AGE":"15","YOB":"1997","CLUB":"NYAC","PROVINCE":"Ontario","DATE":"2012-08-18","MEET":"2012 Ontario Summer Games","TIME":"1:57.38","FINA":"606"},{"RANK":"29","ATHLETES":"Aleman, Antonio-Guy","AGE":"15","YOB":"1995","CLUB":"UL","PROVINCE":"Québec","DATE":"2011-11-26","MEET":"Rencontre provinciale P1-P2","TIME":"1:57.53","FINA":"604"},{"RANK":"30","ATHLETES":"Arafa, Ali Mahmoud","AGE":"15","YOB":"1996","CLUB":"ESWIM","PROVINCE":"Ontario","DATE":"2012-02-19","MEET":"2012 Speedo Eastern Canadian Championships","TIME":"1:57.69","FINA":"601"},{"RANK":"31","ATHLETES":"Monette, Thomas","AGE":"15","YOB":"1997","CLUB":"CAO","PROVINCE":"Québec","DATE":"2012-08-01","MEET":"Finale provinciale des Jeux du Québec 2012","TIME":"1:57.74","FINA":"601"},{"RANK":"32","ATHLETES":"Hamilton, Alexander","AGE":"15","YOB":"1995","CLUB":"NYAC","PROVINCE":"Ontario","DATE":"2011-10-16","MEET":"2011 Hall of Fame Meet","TIME":"1:57.76","FINA":"600"},{"RANK":"33","ATHLETES":"Piekarski, Jacob","AGE":"15","YOB":"1996","CLUB":"LSC","PROVINCE":"Ontario","DATE":"2012-03-01","MEET":"2012 SC Junior & PARA Provincials","TIME":"1:57.86","FINA":"599"},{"RANK":"34","ATHLETES":"Berger, Geraint","AGE":"15","YOB":"1996","CLUB":"HTAC","PROVINCE":"Nova Scotia","DATE":"2012-03-03","MEET":"East Coast Short Course Championship","TIME":"1:57.95","FINA":"597"},{"RANK":"34","ATHLETES":"Beaudry, Simon","AGE":"15","YOB":"1996","CLUB":"CAMO","PROVINCE":"Québec","DATE":"2011-12-16","MEET":"Invitation provinciale P1-P2 de Noël 2011","TIME":"1:57.95","FINA":"597"},{"RANK":"36","ATHLETES":"Bédard, Jérémie","AGE":"15","YOB":"1997","CLUB":"SAMAK","PROVINCE":"Québec","DATE":"2012-02-16","MEET":"2012 Speedo Eastern Canadian Championships","TIME":"1:58.06","FINA":"596"},{"RANK":"37","ATHLETES":"Guest, James","AGE":"15","YOB":"1996","CLUB":"PCSC","PROVINCE":"Québec","DATE":"2011-12-18","MEET":"Invitation Pointe-Claire Provincial 2 2011","TIME":"1:58.07","FINA":"596"},{"RANK":"38","ATHLETES":"Gour, Mitchell","AGE":"15","YOB":"1996","CLUB":"OAK","PROVINCE":"Ontario","DATE":"2011-12-11","MEET":"13th Annual Paul Bergen Junior Int'l Invitational","TIME":"1:58.10","FINA":"595"},{"RANK":"39","ATHLETES":"Binder, Andrew","AGE":"15","YOB":"1996","CLUB":"WEST","PROVINCE":"Ontario","DATE":"2011-12-10","MEET":"Team Aquatic Supplies Dash for Cash","TIME":"1:58.27","FINA":"593"},{"RANK":"40","ATHLETES":"MacDonald, Tyson","AGE":"15","YOB":"1996","CLUB":"SWA","PROVINCE":"Ontario","DATE":"2012-04-21","MEET":"Division 2 Team Championships","TIME":"1:58.47","FINA":"590"},{"RANK":"41","ATHLETES":"Gratton, Frédéric","AGE":"15","YOB":"1997","CLUB":"GAMIN","PROVINCE":"Québec","DATE":"2012-08-01","MEET":"Finale provinciale des Jeux du Québec 2012","TIME":"1:58.70","FINA":"586"},{"RANK":"42","ATHLETES":"Bélanger, Samuel","AGE":"15","YOB":"1997","CLUB":"UL","PROVINCE":"Québec","DATE":"2012-08-01","MEET":"Finale provinciale des Jeux du Québec 2012","TIME":"1:58.72","FINA":"586"},{"RANK":"43","ATHLETES":"Gallant, Yvon","AGE":"15","YOB":"1996","CLUB":"PPO","PROVINCE":"Québec","DATE":"2012-01-28","MEET":"Nouvelle année P1-P2 (25m) sans finales AM","TIME":"1:58.79","FINA":"585"},{"RANK":"44","ATHLETES":"Wang, Samuel","AGE":"15","YOB":"1996","CLUB":"SHER","PROVINCE":"Québec","DATE":"2011-10-30","MEET":"Invitation provinciale Halloween P1-P2, 2011","TIME":"1:58.85","FINA":"584"},{"RANK":"45","ATHLETES":"Zou, Zhaoxin","AGE":"15","YOB":"1996","CLUB":"WDSC","PROVINCE":"British Columbia","DATE":"2012-01-28","MEET":"VPSC Dash For Cash","TIME":"1:58.86","FINA":"584"},{"RANK":"46","ATHLETES":"Takahashi, Andrew","AGE":"15","YOB":"1996","CLUB":"VPSC","PROVINCE":"British Columbia","DATE":"2012-03-02","MEET":"2012 TAS SwimBC SC AAA Championships","TIME":"1:59.11","FINA":"580"},{"RANK":"47","ATHLETES":"Gardiman, Stefano","AGE":"15","YOB":"1996","CLUB":"COBRA","PROVINCE":"Ontario","DATE":"2011-12-02","MEET":"Youth Cup","TIME":"1:59.42","FINA":"576"},{"RANK":"48","ATHLETES":"Dundas, Jordan","AGE":"15","YOB":"1996","CLUB":"NORAC","PROVINCE":"Ontario","DATE":"2012-03-01","MEET":"2012 SC Junior & PARA Provincials","TIME":"1:59.43","FINA":"576"},{"RANK":"49","ATHLETES":"Choboter, Noah","AGE":"15","YOB":"1996","CLUB":"ROD","PROVINCE":"Saskatchewan","DATE":"2011-12-18","MEET":"Invitation de Noël P1-P2","TIME":"1:59.62","FINA":"573"},{"RANK":"50","ATHLETES":"VanderHelm, Adrian","AGE":"15","YOB":"1995","CLUB":"BTSC","PROVINCE":"Ontario","DATE":"2011-12-02","MEET":"Youth Cup","TIME":"1:59.68","FINA":"572"}],"errors":[],"meta":{"delimiter":"|","linebreak":"\n","aborted":false,"truncated":false,"cursor":4993,"fields":["RANK","ATHLETES","AGE","YOB","CLUB","PROVINCE","DATE","MEET","TIME","FINA"]}}