{"data":[{"RANK":"1","ATHLETES":"Kay, Philip","AGE":"17","YOB":"1999","CLUB":"NYAC","PROVINCE":"Ontario","DATE":"2016-12-18","MEET":"2016 Ontario Junior International","TIME":"2:00.69","FINA":"679"},{"RANK":"2","ATHLETES":"Gerlach, Daniel","AGE":"17","YOB":"1999","CLUB":"EKSC","PROVINCE":"Alberta","DATE":"2016-12-17","MEET":"JP Fiset Invitational","TIME":"2:01.89","FINA":"659"},{"RANK":"3","ATHLETES":"Neilson, Achilles","AGE":"17","YOB":"1999","CLUB":"CASC","PROVINCE":"Alberta","DATE":"2016-12-18","MEET":"2016 Ontario Junior International","TIME":"2:02.35","FINA":"652"},{"RANK":"4","ATHLETES":"Lafontaine-Giguère, Thomas","AGE":"17","YOB":"1999","CLUB":"NN","PROVINCE":"Québec","DATE":"2016-12-18","MEET":"2016 Ontario Junior International","TIME":"2:02.39","FINA":"651"},{"RANK":"5","ATHLETES":"Klahsen, Matthew","AGE":"17","YOB":"1999","CLUB":"CAJ","PROVINCE":"Ontario","DATE":"2016-12-18","MEET":"2016 Ontario Junior International","TIME":"2:02.55","FINA":"649"},{"RANK":"6","ATHLETES":"Dufresne, Jean-Philippe","AGE":"17","YOB":"1999","CLUB":"ROD","PROVINCE":"Saskatchewan","DATE":"2016-12-10","MEET":"2016 Man/Sask SC Provincial Championships","TIME":"2:03.98","FINA":"626"},{"RANK":"7","ATHLETES":"Goodman, Graeme","AGE":"17","YOB":"1999","CLUB":"TSC","PROVINCE":"Ontario","DATE":"2016-12-18","MEET":"2016 Ontario Junior International","TIME":"2:04.74","FINA":"615"},{"RANK":"8","ATHLETES":"Pouliot, David","AGE":"17","YOB":"1999","CLUB":"CAMQ","PROVINCE":"Québec","DATE":"2016-12-11","MEET":"Défi Nez-Rouge 2016","TIME":"2:05.52","FINA":"604"},{"RANK":"9","ATHLETES":"Wright, Nicholas","AGE":"17","YOB":"1999","CLUB":"NEW","PROVINCE":"Ontario","DATE":"2017-01-15","MEET":"2017 Etobicoke A - B Meet","TIME":"2:06.31","FINA":"592"},{"RANK":"10","ATHLETES":"Boily-Dufour, Samuel","AGE":"17","YOB":"1998","CLUB":"LU","PROVINCE":"Ontario","DATE":"2016-11-26","MEET":"OUA deBray Divisional Championships","TIME":"2:07.17","FINA":"580"},{"RANK":"10","ATHLETES":"Hopkins, Eric","AGE":"17","YOB":"1999","CLUB":"OAK","PROVINCE":"Ontario","DATE":"2016-11-12","MEET":"2016 Age Group International SC","TIME":"2:07.17","FINA":"580"},{"RANK":"12","ATHLETES":"Lasinski, Samuel","AGE":"17","YOB":"1999","CLUB":"KISU","PROVINCE":"British Columbia","DATE":"2017-03-04","MEET":"2017 SwimBC SC AAA Championships","TIME":"2:07.32","FINA":"578"},{"RANK":"13","ATHLETES":"Jensen, Ethan","AGE":"17","YOB":"1999","CLUB":"KCS","PROVINCE":"British Columbia","DATE":"2016-12-10","MEET":"24th Annual MJB Law Classic","TIME":"2:07.97","FINA":"570"},{"RANK":"14","ATHLETES":"Phillips, Ethan","AGE":"17","YOB":"1999","CLUB":"ISC","PROVINCE":"British Columbia","DATE":"2016-10-29","MEET":"2016 NRST Fall Invitational","TIME":"2:08.02","FINA":"569"},{"RANK":"15","ATHLETES":"Vanherk, Brendan","AGE":"17","YOB":"1999","CLUB":"BLEN","PROVINCE":"Ontario","DATE":"2016-11-27","MEET":"LAC Nothers Fall Invitational","TIME":"2:08.03","FINA":"569"},{"RANK":"16","ATHLETES":"Skuse, Conner","AGE":"17","YOB":"1999","CLUB":"PSW","PROVINCE":"British Columbia","DATE":"2017-03-04","MEET":"2017 SwimBC SC AAA Championships","TIME":"2:08.49","FINA":"563"},{"RANK":"17","ATHLETES":"Hill, Steven","AGE":"17","YOB":"1999","CLUB":"CP","PROVINCE":"Alberta","DATE":"2016-12-17","MEET":"JP Fiset Invitational","TIME":"2:08.58","FINA":"562"},{"RANK":"18","ATHLETES":"Mcgill, Matt","AGE":"17","YOB":"1999","CLUB":"NEW","PROVINCE":"Ontario","DATE":"2017-02-05","MEET":"2017 Central Region B Champs","TIME":"2:08.93","FINA":"557"},{"RANK":"19","ATHLETES":"Cole, Jayden","AGE":"17","YOB":"1999","CLUB":"GO","PROVINCE":"Ontario","DATE":"2016-12-18","MEET":"2016 Ontario Junior International","TIME":"2:08.95","FINA":"557"},{"RANK":"20","ATHLETES":"Potaka, Tanner","AGE":"17","YOB":"1999","CLUB":"KSC","PROVINCE":"Alberta","DATE":"2016-10-28","MEET":"Cascade Speed Meet","TIME":"2:08.96","FINA":"557"},{"RANK":"21","ATHLETES":"Locis, Ethan","AGE":"17","YOB":"1999","CLUB":"CAJ","PROVINCE":"Ontario","DATE":"2016-10-29","MEET":"Joe Kerkhoven Memorial Walker Invitational","TIME":"2:08.98","FINA":"556"},{"RANK":"22","ATHLETES":"Jensen, Ryan","AGE":"17","YOB":"1999","CLUB":"GMAC","PROVINCE":"Ontario","DATE":"2017-02-25","MEET":"WOSA SC Regionals","TIME":"2:09.56","FINA":"549"},{"RANK":"23","ATHLETES":"Intas, Dominykas","AGE":"17","YOB":"1999","CLUB":"RAMAC","PROVINCE":"Ontario","DATE":"2016-11-06","MEET":"Stingrays Fall Invitational","TIME":"2:09.90","FINA":"545"},{"RANK":"24","ATHLETES":"Kuntz, Samuel","AGE":"17","YOB":"1999","CLUB":"MUSAC","PROVINCE":"Ontario","DATE":"2016-12-18","MEET":"Ontario Team Showdown","TIME":"2:10.55","FINA":"536"},{"RANK":"25","ATHLETES":"Wormald, Lukas","AGE":"17","YOB":"1999","CLUB":"ROW","PROVINCE":"Ontario","DATE":"2016-12-18","MEET":"2016 Ontario Junior International","TIME":"2:10.63","FINA":"535"},{"RANK":"26","ATHLETES":"Lin, Johnnie","AGE":"17","YOB":"1999","CLUB":"APEX","PROVINCE":"Ontario","DATE":"2017-02-05","MEET":"2017 Central Region B Champs","TIME":"2:10.72","FINA":"534"},{"RANK":"27","ATHLETES":"Li, Michael","AGE":"17","YOB":"1999","CLUB":"ROW","PROVINCE":"Ontario","DATE":"2016-11-12","MEET":"Swim International 2016","TIME":"2:10.79","FINA":"534"},{"RANK":"28","ATHLETES":"Beals, Connor","AGE":"17","YOB":"1999","CLUB":"COBRA","PROVINCE":"Ontario","DATE":"2016-11-12","MEET":"2016 Age Group International SC","TIME":"2:10.82","FINA":"533"},{"RANK":"28","ATHLETES":"Cox, Mitchell","AGE":"17","YOB":"1999","CLUB":"MUSAC","PROVINCE":"Ontario","DATE":"2016-12-18","MEET":"Ontario Team Showdown","TIME":"2:10.82","FINA":"533"},{"RANK":"30","ATHLETES":"Goin, Emil","AGE":"17","YOB":"1999","CLUB":"PCSC","PROVINCE":"Québec","DATE":"2016-10-29","MEET":"Festival par équipe - section 1","TIME":"2:10.83","FINA":"533"},{"RANK":"31","ATHLETES":"Di Nizio, Benito","AGE":"17","YOB":"1999","CLUB":"RAMAC","PROVINCE":"Ontario","DATE":"2016-11-12","MEET":"2016 Age Group International SC","TIME":"2:10.88","FINA":"532"},{"RANK":"32","ATHLETES":"Kischitzky, Shai","AGE":"17","YOB":"1999","CLUB":"VAC","PROVINCE":"Ontario","DATE":"2017-02-05","MEET":"2017 Central Region B Champs","TIME":"2:10.93","FINA":"532"},{"RANK":"33","ATHLETES":"Bilic, Jeremy","AGE":"17","YOB":"1999","CLUB":"UCSC","PROVINCE":"Alberta","DATE":"2016-12-17","MEET":"JP Fiset Invitational","TIME":"2:11.34","FINA":"527"},{"RANK":"34","ATHLETES":"Paul, Nolan","AGE":"17","YOB":"1999","CLUB":"SPART","PROVINCE":"British Columbia","DATE":"2017-03-04","MEET":"2017 SwimBC SC AAA Championships","TIME":"2:12.11","FINA":"518"},{"RANK":"35","ATHLETES":"Haberstock, Reece","AGE":"17","YOB":"1999","CLUB":"KISU","PROVINCE":"British Columbia","DATE":"2016-12-10","MEET":"24th Annual MJB Law Classic","TIME":"2:12.17","FINA":"517"},{"RANK":"36","ATHLETES":"Zou, Paul","AGE":"17","YOB":"1999","CLUB":"WDSC","PROVINCE":"British Columbia","DATE":"2016-12-03","MEET":"14th ANNUAL PCS XMAS CRACKER","TIME":"2:12.30","FINA":"515"},{"RANK":"37","ATHLETES":"Haasler, Adrian","AGE":"17","YOB":"1999","CLUB":"OAK","PROVINCE":"Ontario","DATE":"2016-11-12","MEET":"2016 Age Group International SC","TIME":"2:12.31","FINA":"515"},{"RANK":"38","ATHLETES":"Brenken, David","AGE":"17","YOB":"1999","CLUB":"NYAC","PROVINCE":"Ontario","DATE":"2016-10-22","MEET":"Fall Downtown Sprint Meet","TIME":"2:12.40","FINA":"514"},{"RANK":"39","ATHLETES":"Wagner, Damond","AGE":"17","YOB":"1999","CLUB":"GOLD","PROVINCE":"Saskatchewan","DATE":"2016-12-10","MEET":"2016 Man/Sask SC Provincial Championships","TIME":"2:12.47","FINA":"513"},{"RANK":"40","ATHLETES":"Ouyang, Leon","AGE":"17","YOB":"1998","CLUB":"WAT","PROVINCE":"Ontario","DATE":"2016-11-26","MEET":"OUA deBray Divisional Championships","TIME":"2:12.55","FINA":"513"},{"RANK":"41","ATHLETES":"Nadeau, Marc-Antoine","AGE":"17","YOB":"1999","CLUB":"CPC","PROVINCE":"Québec","DATE":"2017-01-21","MEET":"Régionale Aquanautes","TIME":"2:12.63","FINA":"512"},{"RANK":"42","ATHLETES":"Dow, Spencer","AGE":"17","YOB":"1999","CLUB":"YAC","PROVINCE":"Alberta","DATE":"2016-12-03","MEET":"14th ANNUAL PCS XMAS CRACKER","TIME":"2:13.05","FINA":"507"},{"RANK":"43","ATHLETES":"Landry, Noah","AGE":"17","YOB":"2000","CLUB":"PSW","PROVINCE":"British Columbia","DATE":"2017-03-04","MEET":"2017 SwimBC SC AAA Championships","TIME":"2:13.10","FINA":"506"},{"RANK":"44","ATHLETES":"McCole, James","AGE":"17","YOB":"1999","CLUB":"CREST","PROVINCE":"Ontario","DATE":"2017-02-05","MEET":"2017 Central Region B Champs","TIME":"2:13.18","FINA":"505"},{"RANK":"44","ATHLETES":"Jrab, Mohamad","AGE":"17","YOB":"1999","CLUB":"ESWIM","PROVINCE":"Ontario","DATE":"2016-11-12","MEET":"2016 Age Group International SC","TIME":"2:13.18","FINA":"505"},{"RANK":"46","ATHLETES":"Paré, Mikael","AGE":"17","YOB":"1998","CLUB":"UL","PROVINCE":"Québec","DATE":"2016-10-29","MEET":"Festival par équipe - section 1","TIME":"2:13.36","FINA":"503"},{"RANK":"46","ATHLETES":"Landriault, Philippe","AGE":"17","YOB":"1999","CLUB":"CAMO","PROVINCE":"Québec","DATE":"2016-11-12","MEET":"2016 Age Group International SC","TIME":"2:13.36","FINA":"503"},{"RANK":"48","ATHLETES":"Drouin, Benoit","AGE":"17","YOB":"1999","CLUB":"STN","PROVINCE":"Québec","DATE":"2016-10-29","MEET":"Festival par équipe - section 5 sud","TIME":"2:13.54","FINA":"501"},{"RANK":"49","ATHLETES":"Beals, Andrew","AGE":"17","YOB":"1999","CLUB":"COBRA","PROVINCE":"Ontario","DATE":"2016-12-11","MEET":"2016 Central Region Large Team Champs","TIME":"2:13.59","FINA":"501"},{"RANK":"50","ATHLETES":"Zou, Jammy","AGE":"17","YOB":"1999","CLUB":"RAPID","PROVINCE":"British Columbia","DATE":"2017-03-04","MEET":"2017 SwimBC SC AAA Championships","TIME":"2:13.78","FINA":"498"}],"errors":[],"meta":{"delimiter":"|","linebreak":"\n","aborted":false,"truncated":false,"cursor":4733,"fields":["RANK","ATHLETES","AGE","YOB","CLUB","PROVINCE","DATE","MEET","TIME","FINA"]}}