{"data":[{"RANK":"1","ATHLETES":"LeFranc, Jaren","AGE":"18","YOB":"1999","CLUB":"UBCT","PROVINCE":"British Columbia","DATE":"2017-11-24","MEET":"2017 Canada West Swimming Championships","TIME":"28.63","FINA":"685"},{"RANK":"2","ATHLETES":"Greer, Daniel","AGE":"18","YOB":"1999","CLUB":"UVIC","PROVINCE":"British Columbia","DATE":"2018-02-24","MEET":"2018 U Sports Championships","TIME":"28.77","FINA":"676"},{"RANK":"3","ATHLETES":"Johnston, Liam","AGE":"18","YOB":"1998","CLUB":"UOFC","PROVINCE":"Alberta","DATE":"2017-11-24","MEET":"2017 Canada West Swimming Championships","TIME":"28.86","FINA":"669"},{"RANK":"4","ATHLETES":"Chabi, Anis","AGE":"18","YOB":"1999","CLUB":"CAMO","PROVINCE":"Québec","DATE":"2017-12-17","MEET":"Ontario Junior International","TIME":"28.96","FINA":"662"},{"RANK":"5","ATHLETES":"Huang, Mark","AGE":"18","YOB":"1999","CLUB":"WAT","PROVINCE":"Ontario","DATE":"2018-02-10","MEET":"OUA Swimming Championships 2018","TIME":"29.26","FINA":"642"},{"RANK":"6","ATHLETES":"Dery, Benjamin","AGE":"18","YOB":"1999","CLUB":"OTT","PROVINCE":"Québec","DATE":"2018-02-10","MEET":"OUA Swimming Championships 2018","TIME":"29.41","FINA":"632"},{"RANK":"7","ATHLETES":"Mccann Stephens, Colin","AGE":"18","YOB":"1999","CLUB":"OSC","PROVINCE":"Alberta","DATE":"2017-12-16","MEET":"JP Fiset Invitational","TIME":"29.51","FINA":"626"},{"RANK":"8","ATHLETES":"Williams, Kenton","AGE":"18","YOB":"1999","CLUB":"UOFC","PROVINCE":"Alberta","DATE":"2018-02-24","MEET":"2018 U Sports Championships","TIME":"29.53","FINA":"625"},{"RANK":"9","ATHLETES":"Haasler, Adrian","AGE":"18","YOB":"1999","CLUB":"MCGILL","PROVINCE":"Québec","DATE":"2017-11-25","MEET":"Coupe Universitaire 3 - UdeM","TIME":"29.88","FINA":"603"},{"RANK":"10","ATHLETES":"Halpen, Matthew","AGE":"18","YOB":"2000","CLUB":"CP","PROVINCE":"Alberta","DATE":"2018-07-15","MEET":"UCSC Western Finale","TIME":"29.90","FINA":"602"},{"RANK":"10","ATHLETES":"Stoyan, John","AGE":"18","YOB":"1999","CLUB":"WLU","PROVINCE":"Ontario","DATE":"2017-11-26","MEET":"deBray Divisional Championships","TIME":"29.90","FINA":"602"},{"RANK":"10","ATHLETES":"Dow, Spencer","AGE":"18","YOB":"1999","CLUB":"UOFC","PROVINCE":"Alberta","DATE":"2018-02-08","MEET":"UofC Varsity TT","TIME":"29.90","FINA":"602"},{"RANK":"13","ATHLETES":"Godwin, Graeme","AGE":"18","YOB":"1999","CLUB":"LASC","PROVINCE":"Alberta","DATE":"2017-12-16","MEET":"JP Fiset Invitational","TIME":"30.11","FINA":"589"},{"RANK":"14","ATHLETES":"Collins, Theo","AGE":"18","YOB":"1998","CLUB":"NN","PROVINCE":"Québec","DATE":"2017-12-02","MEET":"Invitation Neptune de Noel avec finales - CSPO","TIME":"30.22","FINA":"583"},{"RANK":"15","ATHLETES":"Massé, Gabriel","AGE":"18","YOB":"1999","CLUB":"CNQ","PROVINCE":"Québec","DATE":"2017-12-17","MEET":"Ontario Junior International","TIME":"30.23","FINA":"582"},{"RANK":"16","ATHLETES":"Shortt, Gordon","AGE":"18","YOB":"1999","CLUB":"NHAC","PROVINCE":"Ontario","DATE":"2018-02-04","MEET":"2018 Western Region SC Champs","TIME":"30.35","FINA":"575"},{"RANK":"17","ATHLETES":"Korstanje, Anthonie","AGE":"18","YOB":"1999","CLUB":"BADGR","PROVINCE":"Ontario","DATE":"2018-02-10","MEET":"OUA Swimming Championships 2018","TIME":"30.37","FINA":"574"},{"RANK":"18","ATHLETES":"McCole, James","AGE":"18","YOB":"1999","CLUB":"UG","PROVINCE":"Ontario","DATE":"2018-02-10","MEET":"OUA Swimming Championships 2018","TIME":"30.40","FINA":"573"},{"RANK":"19","ATHLETES":"Chirakorn, Parry","AGE":"18","YOB":"1999","CLUB":"UOFC","PROVINCE":"Alberta","DATE":"2017-11-24","MEET":"2017 Canada West Swimming Championships","TIME":"30.49","FINA":"567"},{"RANK":"20","ATHLETES":"Agouès-Richard, Vincent","AGE":"18","YOB":"1999","CLUB":"CASE","PROVINCE":"Québec","DATE":"2017-12-16","MEET":"CSLA Invitation 13 ans et plus","TIME":"30.51","FINA":"566"},{"RANK":"21","ATHLETES":"Hojda, Bartlomiej","AGE":"18","YOB":"1998","CLUB":"MSSAC","PROVINCE":"Ontario","DATE":"2017-11-11","MEET":"2017 Age Group International SC","TIME":"30.60","FINA":"561"},{"RANK":"22","ATHLETES":"Potaka, Tanner","AGE":"18","YOB":"1999","CLUB":"KSC","PROVINCE":"Alberta","DATE":"2017-12-16","MEET":"JP Fiset Invitational","TIME":"30.68","FINA":"557"},{"RANK":"23","ATHLETES":"Sanchez, H. Andre","AGE":"18","YOB":"1999","CLUB":"WES","PROVINCE":"Ontario","DATE":"2018-02-10","MEET":"OUA Swimming Championships 2018","TIME":"30.80","FINA":"550"},{"RANK":"23","ATHLETES":"Lasinski, Samuel","AGE":"18","YOB":"1999","CLUB":"MCGILL","PROVINCE":"Québec","DATE":"2018-02-24","MEET":"2018 U Sports Championships","TIME":"30.80","FINA":"550"},{"RANK":"25","ATHLETES":"Hao, Max","AGE":"18","YOB":"1999","CLUB":"WAT","PROVINCE":"Ontario","DATE":"2017-11-26","MEET":"deBray Divisional Championships","TIME":"30.82","FINA":"549"},{"RANK":"26","ATHLETES":"Gauthier, Matthew","AGE":"18","YOB":"1999","CLUB":"TRUW","PROVINCE":"British Columbia","DATE":"2017-12-15","MEET":"25th ANNUAL MJB Law Classic SCM","TIME":"30.86","FINA":"547"},{"RANK":"27","ATHLETES":"Taylor, Nicholas","AGE":"18","YOB":"2000","CLUB":"NCSA","PROVINCE":"Alberta","DATE":"2018-07-13","MEET":"UCSC Western Finale","TIME":"30.88","FINA":"546"},{"RANK":"28","ATHLETES":"Aylward, Graeme","AGE":"18","YOB":"2000","CLUB":"MMST","PROVINCE":"Ontario","DATE":"2018-06-25","MEET":"Springridge Farm Club Championships","TIME":"30.92","FINA":"544"},{"RANK":"29","ATHLETES":"Iri, Tarik Murat","AGE":"18","YOB":"1999","CLUB":"TSC","PROVINCE":"Ontario","DATE":"2017-11-03","MEET":"NYAC Cup","TIME":"31.08","FINA":"536"},{"RANK":"30","ATHLETES":"Moir, Ryan","AGE":"18","YOB":"1999","CLUB":"WES","PROVINCE":"Ontario","DATE":"2018-02-10","MEET":"OUA Swimming Championships 2018","TIME":"31.09","FINA":"535"},{"RANK":"30","ATHLETES":"Law, Simon","AGE":"18","YOB":"1999","CLUB":"QUE","PROVINCE":"Ontario","DATE":"2017-11-26","MEET":"deBray Divisional Championships","TIME":"31.09","FINA":"535"},{"RANK":"32","ATHLETES":"Curry, Tristan","AGE":"18","YOB":"1999","CLUB":"WAT","PROVINCE":"Ontario","DATE":"2017-11-26","MEET":"deBray Divisional Championships","TIME":"31.13","FINA":"533"},{"RANK":"32","ATHLETES":"Ralph, Alec","AGE":"18","YOB":"1999","CLUB":"CBSB","PROVINCE":"Newfoundland","DATE":"2017-12-08","MEET":"Invitation Provinciale AA-AAA Pointe-Claire 2017 (SC / LC)","TIME":"31.13","FINA":"533"},{"RANK":"34","ATHLETES":"Drasovean, Christian","AGE":"18","YOB":"2000","CLUB":"LAC","PROVINCE":"Ontario","DATE":"2018-02-04","MEET":"2018 Western Region SC Champs","TIME":"31.17","FINA":"531"},{"RANK":"35","ATHLETES":"Aghazadeh, Mir-Kevin","AGE":"18","YOB":"1999","CLUB":"CDNDG","PROVINCE":"Québec","DATE":"2017-12-16","MEET":"CSLA Invitation 13 ans et plus","TIME":"31.21","FINA":"529"},{"RANK":"36","ATHLETES":"Jensen, Ryan","AGE":"18","YOB":"1999","CLUB":"GMAC","PROVINCE":"Ontario","DATE":"2017-12-08","MEET":"Dash for Cash","TIME":"31.29","FINA":"525"},{"RANK":"37","ATHLETES":"Topping, Jasen","AGE":"18","YOB":"1999","CLUB":"GHAC","PROVINCE":"Ontario","DATE":"2017-12-09","MEET":"Border City Invitational","TIME":"31.36","FINA":"521"},{"RANK":"38","ATHLETES":"Yilmaz, Akgun","AGE":"18","YOB":"1999","CLUB":"TSC","PROVINCE":"Ontario","DATE":"2017-11-03","MEET":"NYAC Cup","TIME":"31.40","FINA":"519"},{"RANK":"39","ATHLETES":"Zhang, Osborn","AGE":"18","YOB":"1999","CLUB":"QUE","PROVINCE":"Ontario","DATE":"2017-11-26","MEET":"deBray Divisional Championships","TIME":"31.42","FINA":"518"},{"RANK":"40","ATHLETES":"Joy Jelicic, Nikolas","AGE":"18","YOB":"1999","CLUB":"DAL","PROVINCE":"Nova Scotia","DATE":"2017-11-17","MEET":"2017 Kemp Fry AUS Invitational","TIME":"31.44","FINA":"518"},{"RANK":"41","ATHLETES":"Beaudin-Bolduc, Nathan","AGE":"18","YOB":"1999","CLUB":"UL","PROVINCE":"Québec","DATE":"2017-12-09","MEET":"Défi Nez-Rouge 2017 groupe d'âge","TIME":"31.53","FINA":"513"},{"RANK":"42","ATHLETES":"Isaac, Jacob","AGE":"18","YOB":"1999","CLUB":"OTT","PROVINCE":"Québec","DATE":"2018-02-15","MEET":"uOttawa Gee Gees Time Trial","TIME":"31.59","FINA":"510"},{"RANK":"43","ATHLETES":"Bélanger, Christophe","AGE":"18","YOB":"2000","CLUB":"CNQ","PROVINCE":"Québec","DATE":"2018-05-05","MEET":"Invitation du Printemps CNQ","TIME":"31.61","FINA":"509"},{"RANK":"44","ATHLETES":"Lin, Johnnie","AGE":"18","YOB":"1999","CLUB":"APEX","PROVINCE":"Ontario","DATE":"2017-11-11","MEET":"2017 Age Group International SC","TIME":"31.68","FINA":"506"},{"RANK":"45","ATHLETES":"Dumas, Zachary","AGE":"18","YOB":"1999","CLUB":"UVIC","PROVINCE":"British Columbia","DATE":"2017-10-28","MEET":"NRST Fall Invitational","TIME":"31.74","FINA":"503"},{"RANK":"45","ATHLETES":"Lavoie, Olivier","AGE":"18","YOB":"1999","CLUB":"NSH","PROVINCE":"Québec","DATE":"2018-03-24","MEET":"Invitation du printemps NSH","TIME":"31.74","FINA":"503"},{"RANK":"47","ATHLETES":"Rotsaert-Smith, Gavin","AGE":"18","YOB":"1999","CLUB":"UG","PROVINCE":"Ontario","DATE":"2017-11-26","MEET":"Fairweather Divisional Championships","TIME":"31.81","FINA":"500"},{"RANK":"48","ATHLETES":"Latkovic, Paul","AGE":"18","YOB":"1999","CLUB":"UOFC","PROVINCE":"Alberta","DATE":"2017-10-21","MEET":"UCSC Fall Start Up","TIME":"31.98","FINA":"492"},{"RANK":"48","ATHLETES":"Pouliot, David","AGE":"18","YOB":"1999","CLUB":"CAMQ","PROVINCE":"Québec","DATE":"2017-11-26","MEET":"Invitation provinciale 2017","TIME":"31.98","FINA":"492"},{"RANK":"48","ATHLETES":"Portmann, Patrik-Thomas","AGE":"18","YOB":"1999","CLUB":"WVOSC","PROVINCE":"British Columbia","DATE":"2017-12-15","MEET":"Rapids FastSwim Classic","TIME":"31.98","FINA":"492"}],"errors":[],"meta":{"delimiter":"|","linebreak":"\n","aborted":false,"truncated":false,"cursor":4582,"fields":["RANK","ATHLETES","AGE","YOB","CLUB","PROVINCE","DATE","MEET","TIME","FINA"]}}