{"data":[{"RANK":"1","ATHLETES":"Selmanovic, Din","AGE":"16","YOB":"1998","CLUB":"ESWIM","PROVINCE":"Ontario","DATE":"2015-02-26","MEET":"Ontario Age Group Championships 2015","TIME":"8:11.22","FINA":"735"},{"RANK":"2","ATHLETES":"Morley, William","AGE":"16","YOB":"1998","CLUB":"TSC","PROVINCE":"Ontario","DATE":"2015-02-26","MEET":"Ontario Age Group Championships 2015","TIME":"8:15.64","FINA":"716"},{"RANK":"3","ATHLETES":"Davila, Rafael","AGE":"16","YOB":"1998","CLUB":"ISC","PROVINCE":"British Columbia","DATE":"2014-12-07","MEET":"2014 12th Annual PCS Xmas Cracker Invitational Meet","TIME":"8:18.88","FINA":"702"},{"RANK":"4","ATHLETES":"Lee, Jong Hoon","AGE":"16","YOB":"1998","CLUB":"ESWIM","PROVINCE":"Ontario","DATE":"2014-10-31","MEET":"Harvest Invitational","TIME":"8:20.47","FINA":"695"},{"RANK":"5","ATHLETES":"Lunga, Dumitru","AGE":"16","YOB":"1998","CLUB":"ESWIM","PROVINCE":"Ontario","DATE":"2014-10-31","MEET":"Harvest Invitational","TIME":"8:20.62","FINA":"694"},{"RANK":"6","ATHLETES":"Phillips, Ethan","AGE":"16","YOB":"1999","CLUB":"KCS","PROVINCE":"British Columbia","DATE":"2015-08-15","MEET":"2015 Western Canada Summer Games","TIME":"8:22.30","FINA":"687"},{"RANK":"7","ATHLETES":"Zou, Paul","AGE":"16","YOB":"1999","CLUB":"WDSC","PROVINCE":"British Columbia","DATE":"2015-08-15","MEET":"2015 Western Canada Summer Games","TIME":"8:25.52","FINA":"674"},{"RANK":"8","ATHLETES":"Zakala, Josh","AGE":"16","YOB":"1998","CLUB":"KAJ","PROVINCE":"British Columbia","DATE":"2014-11-07","MEET":"Vernon Kokanee Swim Club Fall Invitational","TIME":"8:25.90","FINA":"673"},{"RANK":"9","ATHLETES":"Paulins, Sebastian","AGE":"16","YOB":"1998","CLUB":"BRANT","PROVINCE":"Ontario","DATE":"2014-11-21","MEET":"Nothers Fall Invitational","TIME":"8:27.00","FINA":"668"},{"RANK":"10","ATHLETES":"Guo, Aaron","AGE":"16","YOB":"1998","CLUB":"MAC","PROVINCE":"Ontario","DATE":"2015-06-20","MEET":"Whitby Final Time Trial","TIME":"8:27.29","FINA":"667"},{"RANK":"11","ATHLETES":"Lin, Peter","AGE":"16","YOB":"1997","CLUB":"MSSAC","PROVINCE":"Ontario","DATE":"2014-10-31","MEET":"Harvest Invitational","TIME":"8:27.58","FINA":"666"},{"RANK":"12","ATHLETES":"Gilbert, Colin","AGE":"16","YOB":"1998","CLUB":"KCS","PROVINCE":"British Columbia","DATE":"2014-12-12","MEET":"22nd Annual MJB Law Classic","TIME":"8:28.61","FINA":"662"},{"RANK":"13","ATHLETES":"Skuse, Conner","AGE":"16","YOB":"1999","CLUB":"CRKW","PROVINCE":"British Columbia","DATE":"2015-08-15","MEET":"2015 Western Canada Summer Games","TIME":"8:29.76","FINA":"658"},{"RANK":"14","ATHLETES":"Laperle, Vincent","AGE":"16","YOB":"1998","CLUB":"PPO","PROVINCE":"Québec","DATE":"2015-03-01","MEET":"Championnat provincial Junior et Senior (Hiver) - Trophées Dubois","TIME":"8:30.29","FINA":"656"},{"RANK":"15","ATHLETES":"Woinoski, Andrew","AGE":"16","YOB":"1998","CLUB":"SFA","PROVINCE":"British Columbia","DATE":"2014-12-07","MEET":"2014 12th Annual PCS Xmas Cracker Invitational Meet","TIME":"8:32.99","FINA":"645"},{"RANK":"16","ATHLETES":"Ivakhnenko, Anthony","AGE":"16","YOB":"1998","CLUB":"OAK","PROVINCE":"Ontario","DATE":"2015-04-11","MEET":"McDonald's Canadian Record Challenge","TIME":"8:34.00","FINA":"642"},{"RANK":"17","ATHLETES":"Beaudin-Bolduc, Nathan","AGE":"16","YOB":"1999","CLUB":"UL","PROVINCE":"Québec","DATE":"2015-03-01","MEET":"Championnat provincial Junior et Senior (Hiver) - Trophées Dubois","TIME":"8:34.22","FINA":"641"},{"RANK":"18","ATHLETES":"Mccann Stephens, Colin","AGE":"16","YOB":"1999","CLUB":"OSC","PROVINCE":"Alberta","DATE":"2015-08-15","MEET":"2015 Western Canada Summer Games","TIME":"8:35.35","FINA":"636"},{"RANK":"19","ATHLETES":"Gardner, Jacob","AGE":"16","YOB":"1998","CLUB":"MAC","PROVINCE":"Ontario","DATE":"2015-02-26","MEET":"Ontario Age Group Championships 2015","TIME":"8:41.25","FINA":"615"},{"RANK":"20","ATHLETES":"Atkinson, Joseph","AGE":"16","YOB":"1998","CLUB":"NYAC","PROVINCE":"Ontario","DATE":"2015-02-26","MEET":"Ontario Age Group Championships 2015","TIME":"8:42.62","FINA":"610"},{"RANK":"21","ATHLETES":"Jedidi, Melek","AGE":"16","YOB":"1998","CLUB":"CAMO","PROVINCE":"Québec","DATE":"2014-11-02","MEET":"Intra-Club CAMO","TIME":"8:43.30","FINA":"608"},{"RANK":"22","ATHLETES":"Howe, Justin","AGE":"16","YOB":"1997","CLUB":"UVPCS","PROVINCE":"British Columbia","DATE":"2014-12-07","MEET":"2014 12th Annual PCS Xmas Cracker Invitational Meet","TIME":"8:43.39","FINA":"608"},{"RANK":"23","ATHLETES":"Lindsey, Adam","AGE":"16","YOB":"1998","CLUB":"MAC","PROVINCE":"Ontario","DATE":"2015-02-05","MEET":"2015 Central Region SC Champs","TIME":"8:44.10","FINA":"605"},{"RANK":"24","ATHLETES":"Ferland, Nic","AGE":"16","YOB":"1998","CLUB":"GSH","PROVINCE":"Ontario","DATE":"2015-01-16","MEET":"2015 Etobicoke A - B Meet","TIME":"8:44.16","FINA":"605"},{"RANK":"25","ATHLETES":"Lashley, Tariq","AGE":"16","YOB":"1998","CLUB":"ESWIM","PROVINCE":"Ontario","DATE":"2015-01-16","MEET":"2015 Etobicoke A - B Meet","TIME":"8:44.82","FINA":"603"},{"RANK":"26","ATHLETES":"Bennett, Scott","AGE":"16","YOB":"1997","CLUB":"NEW","PROVINCE":"Ontario","DATE":"2014-11-15","MEET":"Newmarket Stingrays Distance Time Trial","TIME":"8:45.36","FINA":"601"},{"RANK":"27","ATHLETES":"Taylor, Liam","AGE":"16","YOB":"1998","CLUB":"LASER","PROVINCE":"Saskatchewan","DATE":"2014-12-19","MEET":"Optimist Prairie Cup 2014","TIME":"8:46.33","FINA":"597"},{"RANK":"28","ATHLETES":"Belo, Samuel","AGE":"16","YOB":"1998","CLUB":"TSC","PROVINCE":"Ontario","DATE":"2015-02-26","MEET":"Ontario Age Group Championships 2015","TIME":"8:46.58","FINA":"597"},{"RANK":"29","ATHLETES":"Bélanger, Édouard","AGE":"16","YOB":"1998","CLUB":"CNQ","PROVINCE":"Québec","DATE":"2014-12-12","MEET":"Défi Nez Rouge","TIME":"8:47.13","FINA":"595"},{"RANK":"30","ATHLETES":"Carmichael, Jordan","AGE":"16","YOB":"1998","CLUB":"MM","PROVINCE":"Manitoba","DATE":"2014-12-11","MEET":"Prairie Winter International 2014","TIME":"8:47.45","FINA":"594"},{"RANK":"31","ATHLETES":"Eastick, Christopher","AGE":"16","YOB":"1998","CLUB":"SLSC","PROVINCE":"Ontario","DATE":"2015-01-30","MEET":"2015 Dave Kensit Memorial Championship Short Course Meet","TIME":"8:48.68","FINA":"590"},{"RANK":"32","ATHLETES":"Mackinnon, Ian","AGE":"16","YOB":"1998","CLUB":"GHAC","PROVINCE":"Ontario","DATE":"2015-01-24","MEET":"2015 GHAC Winter Invitational","TIME":"8:49.33","FINA":"587"},{"RANK":"33","ATHLETES":"Barros, Daniel","AGE":"16","YOB":"1998","CLUB":"ESWIM","PROVINCE":"Ontario","DATE":"2014-10-31","MEET":"Harvest Invitational","TIME":"8:51.47","FINA":"580"},{"RANK":"34","ATHLETES":"Rozo, Rafael Rodrigo","AGE":"16","YOB":"1998","CLUB":"MTAC","PROVINCE":"Ontario","DATE":"2015-02-05","MEET":"2015 Central Region SC Champs","TIME":"8:51.67","FINA":"580"},{"RANK":"35","ATHLETES":"Beyak, Jacob","AGE":"16","YOB":"1998","CLUB":"ISC","PROVINCE":"British Columbia","DATE":"2014-12-07","MEET":"2014 12th Annual PCS Xmas Cracker Invitational Meet","TIME":"8:51.75","FINA":"579"},{"RANK":"36","ATHLETES":"Vallee, Andrew","AGE":"16","YOB":"1998","CLUB":"BRANT","PROVINCE":"Ontario","DATE":"2014-11-21","MEET":"Nothers Fall Invitational","TIME":"8:51.99","FINA":"579"},{"RANK":"37","ATHLETES":"Li, Terry","AGE":"16","YOB":"1998","CLUB":"MSSAC","PROVINCE":"Ontario","DATE":"2014-10-31","MEET":"Harvest Invitational","TIME":"8:52.13","FINA":"578"},{"RANK":"38","ATHLETES":"Cappa, Dominic","AGE":"16","YOB":"1999","CLUB":"LAC","PROVINCE":"Ontario","DATE":"2015-02-06","MEET":"2015 WOSA SC Regional Championships","TIME":"8:52.39","FINA":"577"},{"RANK":"39","ATHLETES":"De Robles, Nickolai","AGE":"16","YOB":"1998","CLUB":"CAMO","PROVINCE":"Québec","DATE":"2014-12-05","MEET":"Invitation de Noël A-AA-AAA en 25 mètres","TIME":"8:52.98","FINA":"575"},{"RANK":"40","ATHLETES":"Villalobos, Rodrigo","AGE":"16","YOB":"1998","CLUB":"ESWIM","PROVINCE":"Ontario","DATE":"2014-10-31","MEET":"Harvest Invitational","TIME":"8:53.04","FINA":"575"},{"RANK":"41","ATHLETES":"Jedidi, Fedi","AGE":"16","YOB":"1998","CLUB":"CAMO","PROVINCE":"Québec","DATE":"2014-11-02","MEET":"Intra-Club CAMO","TIME":"8:53.53","FINA":"574"},{"RANK":"42","ATHLETES":"Carpentier, Lévis-Simon","AGE":"16","YOB":"1998","CLUB":"UL","PROVINCE":"Québec","DATE":"2014-12-12","MEET":"Défi Nez Rouge","TIME":"8:54.00","FINA":"572"},{"RANK":"43","ATHLETES":"Rendall, Eric","AGE":"16","YOB":"1997","CLUB":"UCSC","PROVINCE":"Alberta","DATE":"2014-11-21","MEET":"UCSC Distance & IM Challenge","TIME":"8:54.26","FINA":"571"},{"RANK":"44","ATHLETES":"Blomme, Adam","AGE":"16","YOB":"1998","CLUB":"MAC","PROVINCE":"Ontario","DATE":"2015-02-11","MEET":"MAC Time Trial #5","TIME":"8:57.51","FINA":"561"},{"RANK":"45","ATHLETES":"Thompson, Nicholas","AGE":"16","YOB":"1998","CLUB":"BAD","PROVINCE":"Ontario","DATE":"2014-11-07","MEET":"BAD Invitational","TIME":"8:58.79","FINA":"557"},{"RANK":"46","ATHLETES":"Mccabe, Cameron","AGE":"16","YOB":"1998","CLUB":"MSSAC","PROVINCE":"Ontario","DATE":"2015-01-25","MEET":"38th Annual Cindy Nicholas Swim Classic","TIME":"8:59.01","FINA":"556"},{"RANK":"47","ATHLETES":"Young, Bayley","AGE":"16","YOB":"1998","CLUB":"GO","PROVINCE":"Ontario","DATE":"2015-02-26","MEET":"Ontario Age Group Championships 2015","TIME":"8:59.22","FINA":"556"},{"RANK":"48","ATHLETES":"Egarhos, Jake","AGE":"16","YOB":"1998","CLUB":"ROD","PROVINCE":"Saskatchewan","DATE":"2014-10-23","MEET":"Saskatoon Goldfins Swim Club 38th Annual Invitational Open Swim Meet","TIME":"9:00.08","FINA":"553"},{"RANK":"49","ATHLETES":"Longcroft-Harris, Aiden","AGE":"16","YOB":"1998","CLUB":"","PROVINCE":"","DATE":"2015-01-11","MEET":"2015 PCS Blue-Gold Time Trial #1","TIME":"9:00.18","FINA":"553"},{"RANK":"50","ATHLETES":"Kamminga, Frederik","AGE":"16","YOB":"1998","CLUB":"OSC","PROVINCE":"Alberta","DATE":"2015-01-09","MEET":"Blue Bears","TIME":"9:00.31","FINA":"552"}],"errors":[],"meta":{"delimiter":"|","linebreak":"\n","aborted":false,"truncated":false,"cursor":4912,"fields":["RANK","ATHLETES","AGE","YOB","CLUB","PROVINCE","DATE","MEET","TIME","FINA"]}}