{"data":[{"RANK":"1","ATHLETES":"Mastromatteo, Gabe","AGE":"12","YOB":"2002","CLUB":"KSS","PROVINCE":"Ontario","DATE":"2015-03-15","MEET":"ManSask Open Championships","TIME":"4:54.67","FINA":"510"},{"RANK":"2","ATHLETES":"Lau, Alvin","AGE":"12","YOB":"2001","CLUB":"MST~","PROVINCE":"Ontario","DATE":"2014-11-07","MEET":"BAD Invitational","TIME":"5:08.98","FINA":"442"},{"RANK":"3","ATHLETES":"Cyr, Mathieu","AGE":"12","YOB":"2002","CLUB":"UCSC","PROVINCE":"Alberta","DATE":"2015-03-06","MEET":"2015 Speedo Alberta Age Group Championships SC","TIME":"5:09.59","FINA":"440"},{"RANK":"4","ATHLETES":"Kim, Joshua","AGE":"12","YOB":"2002","CLUB":"LOSC","PROVINCE":"British Columbia","DATE":"2014-12-07","MEET":"2014 12th Annual PCS Xmas Cracker Invitational Meet","TIME":"5:09.78","FINA":"439"},{"RANK":"5","ATHLETES":"Pratt, Cole","AGE":"12","YOB":"2002","CLUB":"CASC","PROVINCE":"Alberta","DATE":"2015-03-06","MEET":"2015 Speedo Alberta Age Group Championships SC","TIME":"5:14.01","FINA":"421"},{"RANK":"6","ATHLETES":"Li, Stanford","AGE":"12","YOB":"2002","CLUB":"PCSC","PROVINCE":"Québec","DATE":"2015-04-25","MEET":"Section 1 - Festival par équipe","TIME":"5:14.04","FINA":"421"},{"RANK":"7","ATHLETES":"Nordstrom, Josh","AGE":"12","YOB":"2002","CLUB":"EKSC","PROVINCE":"Alberta","DATE":"2014-12-07","MEET":"2014 12th Annual PCS Xmas Cracker Invitational Meet","TIME":"5:15.40","FINA":"416"},{"RANK":"8","ATHLETES":"Milanovich, Alexander","AGE":"12","YOB":"2002","CLUB":"ESWIM","PROVINCE":"Ontario","DATE":"2014-12-03","MEET":"December 3 Time Trial","TIME":"5:16.29","FINA":"412"},{"RANK":"9","ATHLETES":"Bernard, Graysen","AGE":"12","YOB":"2002","CLUB":"TSC","PROVINCE":"Ontario","DATE":"2014-12-14","MEET":"Invitation provinciale AA-AAA de Noël CAMO 2014","TIME":"5:17.80","FINA":"406"},{"RANK":"10","ATHLETES":"Pei, Samuel","AGE":"12","YOB":"2002","CLUB":"RAPID","PROVINCE":"British Columbia","DATE":"2015-03-06","MEET":"Swim BC AAA Short Course Age Group Championships","TIME":"5:18.15","FINA":"405"},{"RANK":"11","ATHLETES":"Liendo, Joshua","AGE":"12","YOB":"2002","CLUB":"TORCH","PROVINCE":"Ontario","DATE":"2015-06-27","MEET":"2015 Swim Ontario Summer Festival","TIME":"5:19.22","FINA":"401"},{"RANK":"12","ATHLETES":"Robins, Philippe","AGE":"12","YOB":"2002","CLUB":"BBF","PROVINCE":"Québec","DATE":"2014-12-06","MEET":"Invitation de Noël A-AA-AAA en 25 mètres","TIME":"5:21.76","FINA":"392"},{"RANK":"13","ATHLETES":"Bird, Liam","AGE":"12","YOB":"2002","CLUB":"MSSAC","PROVINCE":"Ontario","DATE":"2015-06-27","MEET":"2015 Swim Ontario Summer Festival","TIME":"5:22.53","FINA":"389"},{"RANK":"14","ATHLETES":"Oswald, Brendan","AGE":"12","YOB":"2002","CLUB":"WAC","PROVINCE":"Ontario","DATE":"2015-02-07","MEET":"2015 WOSA SC Regional Championships","TIME":"5:22.77","FINA":"388"},{"RANK":"15","ATHLETES":"Goh, Joel","AGE":"12","YOB":"2002","CLUB":"VPSC","PROVINCE":"British Columbia","DATE":"2014-12-13","MEET":"Fast Swim Classic","TIME":"5:22.95","FINA":"387"},{"RANK":"16","ATHLETES":"Dupuis, Devon","AGE":"12","YOB":"2002","CLUB":"WDSC","PROVINCE":"British Columbia","DATE":"2015-03-06","MEET":"Swim BC AAA Short Course Age Group Championships","TIME":"5:23.34","FINA":"386"},{"RANK":"17","ATHLETES":"Lewington, Mackenzie","AGE":"12","YOB":"2002","CLUB":"PGB","PROVINCE":"British Columbia","DATE":"2015-03-06","MEET":"Swim BC AAA Short Course Age Group Championships","TIME":"5:23.51","FINA":"385"},{"RANK":"18","ATHLETES":"Migneault, Justice","AGE":"12","YOB":"2002","CLUB":"HANEY","PROVINCE":"British Columbia","DATE":"2015-03-06","MEET":"Swim BC AAA Short Course Age Group Championships","TIME":"5:24.22","FINA":"383"},{"RANK":"19","ATHLETES":"Zhang, Tai Lun","AGE":"12","YOB":"2001","CLUB":"NG","PROVINCE":"Québec","DATE":"2014-11-02","MEET":"Invitation ¨A-AA-AAA¨ Halloween 2014","TIME":"5:25.51","FINA":"378"},{"RANK":"20","ATHLETES":"Cruz, Oscar","AGE":"12","YOB":"2002","CLUB":"YMCA","PROVINCE":"Québec","DATE":"2015-02-14","MEET":"Groupe d'age AQUAM - Championnat provincial (Hiver)","TIME":"5:27.16","FINA":"372"},{"RANK":"21","ATHLETES":"MacMillan, Thomas","AGE":"12","YOB":"2002","CLUB":"PERTH","PROVINCE":"Ontario","DATE":"2015-02-21","MEET":"2015 Ontario Winter Festival","TIME":"5:28.55","FINA":"368"},{"RANK":"22","ATHLETES":"Lungu, Nicolas","AGE":"12","YOB":"2001","CLUB":"ELITE","PROVINCE":"Québec","DATE":"2014-12-12","MEET":"Invitation Provinciale AAA Pointe-Claire 2014","TIME":"5:29.15","FINA":"366"},{"RANK":"23","ATHLETES":"Florea, Christian","AGE":"12","YOB":"2002","CLUB":"MSSAC","PROVINCE":"Ontario","DATE":"2015-06-27","MEET":"2015 Swim Ontario Summer Festival","TIME":"5:29.64","FINA":"364"},{"RANK":"24","ATHLETES":"Han, Ryan","AGE":"12","YOB":"2002","CLUB":"SPART","PROVINCE":"British Columbia","DATE":"2014-12-13","MEET":"Spartan Santa LMR","TIME":"5:29.70","FINA":"364"},{"RANK":"25","ATHLETES":"Pfeifer, Scott","AGE":"12","YOB":"2001","CLUB":"SKSC","PROVINCE":"British Columbia","DATE":"2014-11-09","MEET":"2014 Hyack Fall Into Finals","TIME":"5:29.79","FINA":"364"},{"RANK":"26","ATHLETES":"Park, Fergus","AGE":"12","YOB":"2002","CLUB":"NEW","PROVINCE":"Ontario","DATE":"2015-06-27","MEET":"2015 Swim Ontario Summer Festival","TIME":"5:30.13","FINA":"363"},{"RANK":"27","ATHLETES":"Edwards, Drew","AGE":"12","YOB":"2002","CLUB":"EKSC","PROVINCE":"Alberta","DATE":"2015-03-06","MEET":"2015 Speedo Alberta Age Group Championships SC","TIME":"5:30.30","FINA":"362"},{"RANK":"28","ATHLETES":"Durocher, Elliot","AGE":"12","YOB":"2002","CLUB":"BLUE","PROVINCE":"Québec","DATE":"2014-12-06","MEET":"Invitation de Noël A-AA-AAA en 25 mètres","TIME":"5:30.85","FINA":"360"},{"RANK":"29","ATHLETES":"Sava, Michael Andrew","AGE":"12","YOB":"2002","CLUB":"RAMAC","PROVINCE":"Ontario","DATE":"2015-06-27","MEET":"2015 Swim Ontario Summer Festival","TIME":"5:31.87","FINA":"357"},{"RANK":"30","ATHLETES":"Jong, Ethan","AGE":"12","YOB":"2002","CLUB":"MAC","PROVINCE":"Ontario","DATE":"2015-06-27","MEET":"2015 Swim Ontario Summer Festival","TIME":"5:31.94","FINA":"357"},{"RANK":"31","ATHLETES":"Wheatcroft, Thomas","AGE":"12","YOB":"2002","CLUB":"TSC","PROVINCE":"Ontario","DATE":"2015-02-21","MEET":"2015 Ontario Winter Festival","TIME":"5:32.00","FINA":"356"},{"RANK":"32","ATHLETES":"Alaoui, Akram","AGE":"12","YOB":"2003","CLUB":"CAMO","PROVINCE":"Québec","DATE":"2015-04-25","MEET":"Section 1 - Festival par équipe","TIME":"5:32.21","FINA":"356"},{"RANK":"33","ATHLETES":"Belkhelladi, Yanis","AGE":"12","YOB":"2001","CLUB":"ELITE","PROVINCE":"Québec","DATE":"2014-10-26","MEET":"Invitation provinciale Halloween (prélim et finales)","TIME":"5:32.35","FINA":"355"},{"RANK":"34","ATHLETES":"Rambo, Jacob","AGE":"12","YOB":"2002","CLUB":"CSSSC","PROVINCE":"British Columbia","DATE":"2015-01-24","MEET":"38th annual KAJ SnowFest","TIME":"5:32.77","FINA":"354"},{"RANK":"35","ATHLETES":"Qu, Allen","AGE":"12","YOB":"2002","CLUB":"UCSC","PROVINCE":"Alberta","DATE":"2014-11-22","MEET":"UCSC Distance & IM Challenge","TIME":"5:32.98","FINA":"353"},{"RANK":"36","ATHLETES":"Placek, Ethan","AGE":"12","YOB":"2001","CLUB":"WS","PROVINCE":"Ontario","DATE":"2014-11-13","MEET":"PICK November Class II Time Trial","TIME":"5:33.31","FINA":"352"},{"RANK":"37","ATHLETES":"Tong, Eric","AGE":"12","YOB":"2002","CLUB":"RAPID","PROVINCE":"British Columbia","DATE":"2015-02-21","MEET":"AAA Time Trial","TIME":"5:33.46","FINA":"352"},{"RANK":"38","ATHLETES":"Côté, Jonathan","AGE":"12","YOB":"2002","CLUB":"UL","PROVINCE":"Québec","DATE":"2014-12-13","MEET":"Défi Nez Rouge","TIME":"5:33.48","FINA":"352"},{"RANK":"39","ATHLETES":"Lapshin, Alexandr","AGE":"12","YOB":"2003","CLUB":"OSC","PROVINCE":"Alberta","DATE":"2015-07-26","MEET":"UCSC Western National Finale","TIME":"5:33.53","FINA":"352"},{"RANK":"40","ATHLETES":"Wheeler, Myles","AGE":"12","YOB":"2002","CLUB":"SPART","PROVINCE":"British Columbia","DATE":"2014-12-13","MEET":"Spartan Santa LMR","TIME":"5:33.61","FINA":"351"},{"RANK":"41","ATHLETES":"Yarmolau, Eugene","AGE":"12","YOB":"2002","CLUB":"NKB","PROVINCE":"Ontario","DATE":"2015-02-21","MEET":"2015 Ontario Winter Festival","TIME":"5:33.98","FINA":"350"},{"RANK":"42","ATHLETES":"Poulos, George","AGE":"12","YOB":"2002","CLUB":"ESWIM","PROVINCE":"Ontario","DATE":"2015-01-18","MEET":"2015 Etobicoke A - B Meet","TIME":"5:34.84","FINA":"347"},{"RANK":"43","ATHLETES":"Kus, Patrick","AGE":"12","YOB":"2002","CLUB":"ESWIM","PROVINCE":"Ontario","DATE":"2015-02-28","MEET":"Steve Kingston Memorial Swim Meet","TIME":"5:35.06","FINA":"347"},{"RANK":"44","ATHLETES":"Sue, Eric","AGE":"12","YOB":"2002","CLUB":"HYACK","PROVINCE":"British Columbia","DATE":"2015-02-15","MEET":"2015 SWIM BC SHORT COURSE AA CHAMPIONSHIPS","TIME":"5:35.16","FINA":"346"},{"RANK":"45","ATHLETES":"Darwish, Yousef","AGE":"12","YOB":"2002","CLUB":"HAC","PROVINCE":"Ontario","DATE":"2015-02-21","MEET":"2015 Ontario Winter Festival","TIME":"5:35.72","FINA":"345"},{"RANK":"46","ATHLETES":"Phillips, Brayden","AGE":"12","YOB":"2002","CLUB":"PGB","PROVINCE":"British Columbia","DATE":"2015-02-15","MEET":"2015 SWIM BC SHORT COURSE AA CHAMPIONSHIPS","TIME":"5:36.04","FINA":"344"},{"RANK":"47","ATHLETES":"Field, Sean","AGE":"12","YOB":"2002","CLUB":"PCSC","PROVINCE":"Québec","DATE":"2014-12-12","MEET":"Invitation Provinciale AAA Pointe-Claire 2014","TIME":"5:36.95","FINA":"341"},{"RANK":"48","ATHLETES":"Yu, Larry","AGE":"12","YOB":"2002","CLUB":"ISC","PROVINCE":"British Columbia","DATE":"2015-01-24","MEET":"2015 VIR SC Regional Championships","TIME":"5:37.24","FINA":"340"},{"RANK":"49","ATHLETES":"Brown, Eric","AGE":"12","YOB":"2002","CLUB":"PCSC","PROVINCE":"Québec","DATE":"2015-04-25","MEET":"Section 1 - Festival par équipe","TIME":"5:37.25","FINA":"340"},{"RANK":"50","ATHLETES":"Ferguson, Tristan","AGE":"12","YOB":"2001","CLUB":"OAK","PROVINCE":"Ontario","DATE":"2014-11-21","MEET":"Nothers Fall Invitational","TIME":"5:37.47","FINA":"339"}],"errors":[],"meta":{"delimiter":"|","linebreak":"\n","aborted":false,"truncated":false,"cursor":5006,"fields":["RANK","ATHLETES","AGE","YOB","CLUB","PROVINCE","DATE","MEET","TIME","FINA"]}}